{"title_prefix": null, "title": "Hymns", "title_part_number": null, "title_part_name": null, "subtitle": null, "composer": null, "performer": "Adam, Eugenie", "arranger": null, "original_composer": null, "label": "B2676 De Luxe Reproducing Roll Corp.", "publisher": "De Luxe Reproducing Roll Corp.", "number": "B2676", "publish_date": "[1923]", "publish_place": "N.Y.", "recording_date": null, "type": "welte-licensee", "PURL": "https://purl.stanford.edu/yd091xk8735", "image_url": "https://stacks.stanford.edu/image/iiif/yd091xk8735/yd091xk8735_0001_gs/info.json", "searchtitle": "Adam - Hymns", "for_catalog": {"composer": "", "arranger": "", "performer": "Adam, Eugenie", "work": "Hymns"}, "NOTE_MIDI_TPQ": 480, "IMAGE_WIDTH": "4096", "IMAGE_LENGTH": "90120", "FIRST_HOLE": "8356", "AVG_HOLE_WIDTH": "19.84", "holeData": [{"x": 502, "y": 8356, "w": 21, "h": 54, "m": 20}, {"x": 368, "y": 8357, "w": 20, "h": 55, "m": 16}, {"x": 434, "y": 8357, "w": 20, "h": 54, "m": 18}, {"x": 569, "y": 8357, "w": 20, "h": 54, "m": 22}, {"x": 3422, "y": 8383, "w": 20, "h": 56, "m": 107}, {"x": 3488, "y": 8384, "w": 20, "h": 56, "m": 109}, {"x": 3555, "y": 8384, "w": 20, "h": 56, "m": 111}, {"x": 3623, "y": 8387, "w": 20, "h": 55, "m": 113}, {"x": 467, "y": 8555, "w": 20, "h": 210, "m": 19}, {"x": 537, "y": 8565, "w": 20, "h": 200, "m": 21}, {"x": 3523, "y": 8600, "w": 19, "h": 211, "m": 110}, {"x": 3455, "y": 8601, "w": 19, "h": 209, "m": 108}, {"x": 401, "y": 8817, "w": 20, "h": 56, "m": 17}, {"x": 3590, "y": 8854, "w": 20, "h": 55, "m": 112}, {"x": 503, "y": 8923, "w": 21, "h": 29, "m": 20}, {"x": 435, "y": 8924, "w": 20, "h": 46, "m": 18}, {"x": 3489, "y": 8979, "w": 20, "h": 19, "m": 109}, {"x": 1374, "y": 9088, "w": 20, "h": 207, "m": 46, "v": 70}, {"x": 1776, "y": 9100, "w": 19, "h": 206, "m": 58, "v": 70}, {"x": 2011, "y": 9109, "w": 20, "h": 189, "m": 65, "v": 70}, {"x": 1909, "y": 9110, "w": 21, "h": 179, "m": 62, "v": 70}, {"x": 2177, "y": 9111, "w": 20, "h": 225, "m": 70, "v": 84}, {"x": 2312, "y": 9114, "w": 19, "h": 233, "m": 74, "v": 84}, {"x": 3388, "y": 9148, "w": 19, "h": 55, "m": 106}, {"x": 467, "y": 9257, "w": 21, "h": 46, "m": 19}, {"x": 1374, "y": 9455, "w": 20, "h": 531, "m": 46, "v": 71}, {"x": 1674, "y": 9519, "w": 20, "h": 485, "m": 55, "v": 73}, {"x": 3456, "y": 9522, "w": 18, "h": 28, "m": 108}, {"x": 1944, "y": 9529, "w": 20, "h": 476, "m": 63, "v": 73}, {"x": 2076, "y": 9539, "w": 21, "h": 477, "m": 67, "v": 90}, {"x": 2177, "y": 9540, "w": 20, "h": 468, "m": 70, "v": 90}, {"x": 3422, "y": 9548, "w": 19, "h": 53, "m": 107}, {"x": 2344, "y": 9550, "w": 21, "h": 449, "m": 75, "v": 90}, {"x": 435, "y": 9579, "w": 20, "h": 55, "m": 18}, {"x": 3556, "y": 9611, "w": 20, "h": 65, "m": 111}, {"x": 3489, "y": 9639, "w": 20, "h": 37, "m": 109}, {"x": 3388, "y": 9727, "w": 20, "h": 47, "m": 106}, {"x": 3524, "y": 10060, "w": 20, "h": 46, "m": 110}, {"x": 1375, "y": 10082, "w": 21, "h": 64, "m": 46, "v": 62}, {"x": 1676, "y": 10085, "w": 20, "h": 63, "m": 55, "v": 62}, {"x": 2079, "y": 10087, "w": 20, "h": 81, "m": 67, "v": 67}, {"x": 1946, "y": 10094, "w": 19, "h": 72, "m": 63, "v": 62}, {"x": 2179, "y": 10096, "w": 20, "h": 64, "m": 70, "v": 67}, {"x": 2346, "y": 10096, "w": 21, "h": 64, "m": 75, "v": 67}, {"x": 539, "y": 10171, "w": 20, "h": 28, "m": 21}, {"x": 3456, "y": 10175, "w": 20, "h": 92, "m": 108}, {"x": 3424, "y": 10211, "w": 20, "h": 56, "m": 107}, {"x": 1376, "y": 10217, "w": 20, "h": 225, "m": 46, "v": 69}, {"x": 1945, "y": 10218, "w": 20, "h": 234, "m": 63, "v": 69}, {"x": 2080, "y": 10230, "w": 19, "h": 224, "m": 67, "v": 84}, {"x": 2179, "y": 10230, "w": 21, "h": 234, "m": 70, "v": 84}, {"x": 1677, "y": 10236, "w": 20, "h": 208, "m": 55, "v": 69}, {"x": 437, "y": 10244, "w": 20, "h": 54, "m": 18}, {"x": 3557, "y": 10293, "w": 20, "h": 55, "m": 111}, {"x": 3390, "y": 10380, "w": 20, "h": 57, "m": 106}, {"x": 1377, "y": 10531, "w": 20, "h": 270, "m": 46, "v": 62}, {"x": 1643, "y": 10578, "w": 20, "h": 288, "m": 54, "v": 61}, {"x": 2046, "y": 10579, "w": 21, "h": 278, "m": 66, "v": 61}, {"x": 2147, "y": 10589, "w": 20, "h": 291, "m": 69, "v": 83}, {"x": 2248, "y": 10589, "w": 21, "h": 281, "m": 72, "v": 83}, {"x": 3425, "y": 10596, "w": 20, "h": 64, "m": 107}, {"x": 1946, "y": 10597, "w": 21, "h": 270, "m": 63, "v": 60}, {"x": 471, "y": 10746, "w": 20, "h": 64, "m": 19}, {"x": 3526, "y": 10794, "w": 20, "h": 55, "m": 110}, {"x": 3390, "y": 10811, "w": 21, "h": 47, "m": 106}, {"x": 372, "y": 10873, "w": 20, "h": 46, "m": 16}, {"x": 1378, "y": 10890, "w": 19, "h": 342, "m": 46, "v": 60}, {"x": 1613, "y": 10901, "w": 20, "h": 349, "m": 53, "v": 60}, {"x": 1779, "y": 10910, "w": 21, "h": 333, "m": 58, "v": 61}, {"x": 3626, "y": 10914, "w": 6, "h": 51, "m": 113}, {"x": 1913, "y": 10946, "w": 20, "h": 305, "m": 62, "v": 61}, {"x": 2015, "y": 10954, "w": 20, "h": 306, "m": 65, "v": 62}, {"x": 2181, "y": 10957, "w": 21, "h": 287, "m": 70, "v": 82}, {"x": 2316, "y": 10967, "w": 20, "h": 297, "m": 74, "v": 82}, {"x": 3426, "y": 10972, "w": 20, "h": 47, "m": 107}, {"x": 440, "y": 10980, "w": 19, "h": 55, "m": 18}, {"x": 3560, "y": 11019, "w": 19, "h": 54, "m": 111}, {"x": 3393, "y": 11171, "w": 19, "h": 71, "m": 106}, {"x": 1379, "y": 11293, "w": 20, "h": 404, "m": 46, "v": 55}, {"x": 1614, "y": 11303, "w": 19, "h": 387, "m": 53, "v": 54}, {"x": 1781, "y": 11304, "w": 20, "h": 377, "m": 58, "v": 54}, {"x": 1914, "y": 11313, "w": 21, "h": 369, "m": 62, "v": 54}, {"x": 2016, "y": 11313, "w": 21, "h": 377, "m": 65, "v": 54}, {"x": 2182, "y": 11315, "w": 21, "h": 414, "m": 70, "v": 76}, {"x": 474, "y": 11555, "w": 20, "h": 54, "m": 19}, {"x": 3528, "y": 11600, "w": 21, "h": 55, "m": 110}, {"x": 3429, "y": 11878, "w": 20, "h": 63, "m": 107}, {"x": 1279, "y": 11954, "w": 20, "h": 269, "m": 43, "v": 58}, {"x": 1682, "y": 11957, "w": 20, "h": 279, "m": 55, "v": 58}, {"x": 2185, "y": 11969, "w": 19, "h": 233, "m": 70, "v": 75}, {"x": 2084, "y": 11977, "w": 21, "h": 269, "m": 67, "v": 75}, {"x": 2319, "y": 11988, "w": 21, "h": 261, "m": 74, "v": 75}, {"x": 442, "y": 11991, "w": 20, "h": 55, "m": 18}, {"x": 475, "y": 12108, "w": 20, "h": 45, "m": 19}, {"x": 3395, "y": 12129, "w": 20, "h": 64, "m": 106}, {"x": 1213, "y": 12294, "w": 20, "h": 363, "m": 41, "v": 61}, {"x": 1617, "y": 12350, "w": 20, "h": 336, "m": 53, "v": 62}, {"x": 3431, "y": 12352, "w": 19, "h": 65, "m": 107}, {"x": 2019, "y": 12386, "w": 20, "h": 311, "m": 65, "v": 63}, {"x": 2186, "y": 12390, "w": 20, "h": 291, "m": 70, "v": 75}, {"x": 2321, "y": 12399, "w": 19, "h": 291, "m": 74, "v": 75}, {"x": 2421, "y": 12401, "w": 20, "h": 282, "m": 77, "v": 75}, {"x": 443, "y": 12404, "w": 20, "h": 64, "m": 18}, {"x": 3564, "y": 12453, "w": 20, "h": 55, "m": 111}, {"x": 3397, "y": 12551, "w": 20, "h": 55, "m": 106}, {"x": 477, "y": 12621, "w": 21, "h": 54, "m": 19}, {"x": 3533, "y": 12661, "w": 20, "h": 56, "m": 110}, {"x": 1214, "y": 12736, "w": 22, "h": 278, "m": 41, "v": 61}, {"x": 1619, "y": 12766, "w": 19, "h": 261, "m": 53, "v": 62}, {"x": 2188, "y": 12779, "w": 20, "h": 234, "m": 70, "v": 73}, {"x": 2021, "y": 12784, "w": 22, "h": 235, "m": 65, "v": 62}, {"x": 2322, "y": 12789, "w": 21, "h": 233, "m": 74, "v": 73}, {"x": 446, "y": 12790, "w": 19, "h": 47, "m": 18}, {"x": 3433, "y": 12796, "w": 19, "h": 64, "m": 107}, {"x": 3566, "y": 12824, "w": 20, "h": 55, "m": 111}, {"x": 3398, "y": 12930, "w": 21, "h": 37, "m": 106}, {"x": 479, "y": 12978, "w": 20, "h": 64, "m": 19}, {"x": 3534, "y": 13030, "w": 20, "h": 45, "m": 110}, {"x": 1283, "y": 13102, "w": 19, "h": 332, "m": 43, "v": 61}, {"x": 1686, "y": 13115, "w": 20, "h": 324, "m": 55, "v": 61}, {"x": 1921, "y": 13133, "w": 20, "h": 325, "m": 62, "v": 61}, {"x": 2088, "y": 13144, "w": 21, "h": 289, "m": 67, "v": 72}, {"x": 2188, "y": 13145, "w": 20, "h": 297, "m": 70, "v": 72}, {"x": 446, "y": 13157, "w": 20, "h": 45, "m": 18}, {"x": 3434, "y": 13165, "w": 20, "h": 43, "m": 107}, {"x": 3567, "y": 13191, "w": 20, "h": 55, "m": 111}, {"x": 3400, "y": 13370, "w": 19, "h": 64, "m": 106}, {"x": 480, "y": 13390, "w": 19, "h": 55, "m": 19}, {"x": 3534, "y": 13433, "w": 21, "h": 46, "m": 110}, {"x": 3434, "y": 13558, "w": 20, "h": 55, "m": 107}, {"x": 1620, "y": 13563, "w": 20, "h": 261, "m": 53, "v": 60}, {"x": 1955, "y": 13564, "w": 20, "h": 244, "m": 63, "v": 61}, {"x": 2023, "y": 13573, "w": 20, "h": 243, "m": 65, "v": 61}, {"x": 2156, "y": 13576, "w": 20, "h": 253, "m": 69, "v": 70}, {"x": 2257, "y": 13576, "w": 21, "h": 298, "m": 72, "v": 70}, {"x": 447, "y": 13587, "w": 20, "h": 63, "m": 18}, {"x": 3567, "y": 13631, "w": 20, "h": 64, "m": 111}, {"x": 3400, "y": 13720, "w": 19, "h": 55, "m": 106}, {"x": 1387, "y": 13991, "w": 20, "h": 908, "m": 46, "v": 51}, {"x": 1621, "y": 14003, "w": 20, "h": 916, "m": 53, "v": 51}, {"x": 1788, "y": 14013, "w": 21, "h": 907, "m": 58, "v": 51}, {"x": 2024, "y": 14013, "w": 20, "h": 756, "m": 65, "v": 51}, {"x": 1922, "y": 14014, "w": 20, "h": 746, "m": 62, "v": 51}, {"x": 2190, "y": 14016, "w": 21, "h": 766, "m": 70, "v": 62}, {"x": 3436, "y": 14098, "w": 19, "h": 64, "m": 107}, {"x": 3401, "y": 14304, "w": 20, "h": 54, "m": 106}, {"x": 3537, "y": 14520, "w": 20, "h": 66, "m": 110}, {"x": 482, "y": 14590, "w": 19, "h": 64, "m": 19}, {"x": 3435, "y": 14935, "w": 20, "h": 54, "m": 107}, {"x": 1387, "y": 15014, "w": 20, "h": 208, "m": 46, "v": 47}, {"x": 1788, "y": 15018, "w": 21, "h": 262, "m": 58, "v": 47}, {"x": 448, "y": 15021, "w": 20, "h": 64, "m": 18}, {"x": 2024, "y": 15027, "w": 20, "h": 218, "m": 65, "v": 47}, {"x": 2190, "y": 15030, "w": 20, "h": 226, "m": 70, "v": 63}, {"x": 2325, "y": 15041, "w": 20, "h": 198, "m": 74, "v": 63}, {"x": 3400, "y": 15096, "w": 20, "h": 46, "m": 106}, {"x": 481, "y": 15138, "w": 20, "h": 65, "m": 19}, {"x": 1387, "y": 15356, "w": 19, "h": 422, "m": 46, "v": 50}, {"x": 1788, "y": 15395, "w": 21, "h": 422, "m": 58, "v": 51}, {"x": 1990, "y": 15396, "w": 20, "h": 413, "m": 64, "v": 51}, {"x": 2090, "y": 15398, "w": 20, "h": 412, "m": 67, "v": 72}, {"x": 2190, "y": 15408, "w": 19, "h": 395, "m": 70, "v": 72}, {"x": 2258, "y": 15417, "w": 20, "h": 395, "m": 72, "v": 72}, {"x": 448, "y": 15426, "w": 19, "h": 54, "m": 18}, {"x": 3435, "y": 15429, "w": 19, "h": 53, "m": 107}, {"x": 3568, "y": 15465, "w": 20, "h": 63, "m": 111}, {"x": 3400, "y": 15650, "w": 19, "h": 56, "m": 106}, {"x": 481, "y": 15684, "w": 19, "h": 54, "m": 19}, {"x": 3535, "y": 15733, "w": 20, "h": 55, "m": 110}, {"x": 1788, "y": 15886, "w": 20, "h": 101, "m": 58, "v": 50}, {"x": 1387, "y": 15893, "w": 19, "h": 73, "m": 46, "v": 50}, {"x": 1990, "y": 15897, "w": 20, "h": 82, "m": 64, "v": 50}, {"x": 2089, "y": 15898, "w": 21, "h": 91, "m": 67, "v": 71}, {"x": 2257, "y": 15909, "w": 21, "h": 83, "m": 72, "v": 71}, {"x": 548, "y": 16033, "w": 22, "h": 28, "m": 21}, {"x": 1352, "y": 16053, "w": 20, "h": 271, "m": 45, "v": 59}, {"x": 1755, "y": 16066, "w": 20, "h": 279, "m": 57, "v": 62}, {"x": 447, "y": 16076, "w": 20, "h": 55, "m": 18}, {"x": 2024, "y": 16084, "w": 19, "h": 271, "m": 65, "v": 64}, {"x": 3435, "y": 16090, "w": 19, "h": 65, "m": 107}, {"x": 3468, "y": 16092, "w": 18, "h": 19, "m": 108}, {"x": 2156, "y": 16097, "w": 21, "h": 269, "m": 69, "v": 77}, {"x": 2258, "y": 16097, "w": 20, "h": 252, "m": 72, "v": 77}, {"x": 2425, "y": 16099, "w": 19, "h": 270, "m": 77, "v": 77}, {"x": 3568, "y": 16110, "w": 19, "h": 73, "m": 111}, {"x": 480, "y": 16274, "w": 19, "h": 54, "m": 19}, {"x": 3399, "y": 16297, "w": 20, "h": 63, "m": 106}, {"x": 3534, "y": 16326, "w": 20, "h": 54, "m": 110}, {"x": 1351, "y": 16430, "w": 20, "h": 118, "m": 45, "v": 63}, {"x": 1755, "y": 16442, "w": 19, "h": 118, "m": 57, "v": 64}, {"x": 2023, "y": 16452, "w": 20, "h": 146, "m": 65, "v": 64}, {"x": 2257, "y": 16455, "w": 21, "h": 147, "m": 72, "v": 81}, {"x": 2156, "y": 16456, "w": 20, "h": 154, "m": 69, "v": 81}, {"x": 1383, "y": 16753, "w": 20, "h": 339, "m": 46, "v": 70}, {"x": 1785, "y": 16792, "w": 21, "h": 314, "m": 58, "v": 70}, {"x": 444, "y": 16802, "w": 20, "h": 54, "m": 18}, {"x": 2187, "y": 16806, "w": 20, "h": 294, "m": 70, "v": 90}, {"x": 2087, "y": 16813, "w": 20, "h": 287, "m": 67, "v": 90}, {"x": 2288, "y": 16815, "w": 20, "h": 287, "m": 73, "v": 90}, {"x": 2389, "y": 16816, "w": 20, "h": 278, "m": 76, "v": 90}, {"x": 3432, "y": 16828, "w": 19, "h": 45, "m": 107}, {"x": 3565, "y": 16838, "w": 20, "h": 64, "m": 111}, {"x": 477, "y": 16971, "w": 20, "h": 55, "m": 19}, {"x": 3397, "y": 17015, "w": 19, "h": 64, "m": 106}, {"x": 3532, "y": 17034, "w": 20, "h": 55, "m": 110}, {"x": 979, "y": 17166, "w": 21, "h": 335, "m": 34, "v": 70}, {"x": 1382, "y": 17181, "w": 20, "h": 327, "m": 46, "v": 70}, {"x": 2019, "y": 17195, "w": 21, "h": 317, "m": 65, "v": 70}, {"x": 2185, "y": 17199, "w": 20, "h": 316, "m": 70, "v": 89}, {"x": 443, "y": 17204, "w": 20, "h": 56, "m": 18}, {"x": 2319, "y": 17209, "w": 21, "h": 325, "m": 74, "v": 90}, {"x": 3430, "y": 17221, "w": 20, "h": 46, "m": 107}, {"x": 3564, "y": 17268, "w": 20, "h": 55, "m": 111}, {"x": 476, "y": 17350, "w": 19, "h": 46, "m": 19}, {"x": 3530, "y": 17411, "w": 20, "h": 46, "m": 110}, {"x": 3394, "y": 17455, "w": 20, "h": 64, "m": 106}, {"x": 1247, "y": 17568, "w": 20, "h": 298, "m": 42, "v": 70}, {"x": 1647, "y": 17581, "w": 21, "h": 290, "m": 54, "v": 70}, {"x": 442, "y": 17592, "w": 20, "h": 56, "m": 18}, {"x": 1950, "y": 17592, "w": 20, "h": 280, "m": 63, "v": 70}, {"x": 2051, "y": 17593, "w": 19, "h": 270, "m": 66, "v": 70}, {"x": 2152, "y": 17595, "w": 19, "h": 280, "m": 69, "v": 90}, {"x": 2252, "y": 17605, "w": 20, "h": 252, "m": 72, "v": 90}, {"x": 3429, "y": 17617, "w": 19, "h": 54, "m": 107}, {"x": 3562, "y": 17636, "w": 19, "h": 64, "m": 111}, {"x": 474, "y": 17763, "w": 20, "h": 74, "m": 19}, {"x": 3393, "y": 17787, "w": 20, "h": 55, "m": 106}, {"x": 3529, "y": 17816, "w": 20, "h": 63, "m": 110}, {"x": 1278, "y": 17951, "w": 20, "h": 289, "m": 43, "v": 70}, {"x": 1681, "y": 17974, "w": 20, "h": 280, "m": 55, "v": 70}, {"x": 3428, "y": 17974, "w": 20, "h": 72, "m": 107}, {"x": 2184, "y": 17988, "w": 20, "h": 270, "m": 70, "v": 90}, {"x": 1514, "y": 17990, "w": 20, "h": 253, "m": 50, "v": 70}, {"x": 1916, "y": 17994, "w": 20, "h": 270, "m": 62, "v": 70}, {"x": 2084, "y": 17996, "w": 20, "h": 270, "m": 67, "v": 90}, {"x": 442, "y": 18020, "w": 20, "h": 47, "m": 18}, {"x": 3561, "y": 18073, "w": 20, "h": 65, "m": 111}, {"x": 3394, "y": 18215, "w": 19, "h": 73, "m": 106}, {"x": 474, "y": 18228, "w": 20, "h": 55, "m": 19}, {"x": 3529, "y": 18288, "w": 20, "h": 55, "m": 110}, {"x": 1045, "y": 18351, "w": 21, "h": 542, "m": 36, "v": 68}, {"x": 1447, "y": 18403, "w": 20, "h": 523, "m": 48, "v": 69}, {"x": 1849, "y": 18434, "w": 20, "h": 506, "m": 60, "v": 70}, {"x": 2018, "y": 18444, "w": 20, "h": 512, "m": 65, "v": 70}, {"x": 2150, "y": 18447, "w": 21, "h": 558, "m": 69, "v": 89}, {"x": 3428, "y": 18450, "w": 20, "h": 54, "m": 107}, {"x": 441, "y": 18453, "w": 20, "h": 56, "m": 18}, {"x": 3561, "y": 18505, "w": 20, "h": 65, "m": 111}, {"x": 3393, "y": 18638, "w": 20, "h": 55, "m": 106}, {"x": 474, "y": 18816, "w": 20, "h": 62, "m": 19}, {"x": 3529, "y": 18989, "w": 21, "h": 65, "m": 110}, {"x": 441, "y": 18994, "w": 20, "h": 55, "m": 18}, {"x": 1045, "y": 18999, "w": 20, "h": 108, "m": 36, "v": 65}, {"x": 1446, "y": 19006, "w": 20, "h": 108, "m": 48, "v": 65}, {"x": 2017, "y": 19018, "w": 20, "h": 145, "m": 65, "v": 65}, {"x": 1849, "y": 19020, "w": 20, "h": 134, "m": 60, "v": 65}, {"x": 474, "y": 19092, "w": 19, "h": 64, "m": 19}, {"x": 1045, "y": 19223, "w": 20, "h": 361, "m": 36, "v": 66}, {"x": 1446, "y": 19239, "w": 20, "h": 351, "m": 48, "v": 67}, {"x": 1983, "y": 19296, "w": 20, "h": 299, "m": 64, "v": 68}, {"x": 2083, "y": 19298, "w": 20, "h": 298, "m": 67, "v": 86}, {"x": 1848, "y": 19306, "w": 20, "h": 298, "m": 60, "v": 68}, {"x": 3427, "y": 19310, "w": 20, "h": 64, "m": 107}, {"x": 2182, "y": 19317, "w": 21, "h": 279, "m": 70, "v": 86}, {"x": 441, "y": 19327, "w": 20, "h": 55, "m": 18}, {"x": 3561, "y": 19366, "w": 20, "h": 64, "m": 111}, {"x": 509, "y": 19469, "w": 21, "h": 27, "m": 20}, {"x": 3393, "y": 19525, "w": 20, "h": 63, "m": 106}, {"x": 474, "y": 19550, "w": 20, "h": 65, "m": 19}, {"x": 543, "y": 19679, "w": 21, "h": 27, "m": 21}, {"x": 1446, "y": 19680, "w": 20, "h": 322, "m": 48, "v": 57}, {"x": 1045, "y": 19683, "w": 20, "h": 313, "m": 36, "v": 57}, {"x": 509, "y": 19729, "w": 21, "h": 38, "m": 20}, {"x": 1782, "y": 19736, "w": 20, "h": 268, "m": 58, "v": 65}, {"x": 1983, "y": 19736, "w": 21, "h": 270, "m": 64, "v": 65}, {"x": 441, "y": 19740, "w": 20, "h": 54, "m": 18}, {"x": 1849, "y": 19747, "w": 20, "h": 260, "m": 60, "v": 62}, {"x": 3428, "y": 19749, "w": 20, "h": 55, "m": 107}, {"x": 3394, "y": 19901, "w": 19, "h": 55, "m": 106}, {"x": 473, "y": 20017, "w": 20, "h": 64, "m": 19}, {"x": 1208, "y": 20141, "w": 22, "h": 962, "m": 41, "v": 50}, {"x": 542, "y": 20160, "w": 20, "h": 29, "m": 21}, {"x": 1613, "y": 20163, "w": 21, "h": 925, "m": 53, "v": 51}, {"x": 1445, "y": 20171, "w": 20, "h": 962, "m": 48, "v": 54}, {"x": 1748, "y": 20191, "w": 19, "h": 907, "m": 57, "v": 59}, {"x": 1847, "y": 20201, "w": 20, "h": 898, "m": 60, "v": 61}, {"x": 2016, "y": 20209, "w": 20, "h": 953, "m": 65, "v": 62}, {"x": 440, "y": 20222, "w": 20, "h": 65, "m": 18}, {"x": 508, "y": 20222, "w": 21, "h": 55, "m": 20}, {"x": 3427, "y": 20232, "w": 20, "h": 63, "m": 107}, {"x": 3392, "y": 20437, "w": 20, "h": 64, "m": 106}, {"x": 472, "y": 20620, "w": 20, "h": 63, "m": 19}, {"x": 3527, "y": 20671, "w": 20, "h": 37, "m": 110}, {"x": 3426, "y": 21152, "w": 20, "h": 64, "m": 107}, {"x": 540, "y": 21231, "w": 20, "h": 29, "m": 21}, {"x": 438, "y": 21276, "w": 20, "h": 65, "m": 18}, {"x": 1611, "y": 21277, "w": 20, "h": 236, "m": 53, "v": 61}, {"x": 2014, "y": 21287, "w": 20, "h": 245, "m": 65, "v": 61}, {"x": 3390, "y": 21341, "w": 20, "h": 55, "m": 106}, {"x": 471, "y": 21430, "w": 19, "h": 56, "m": 19}, {"x": 1208, "y": 21642, "w": 20, "h": 530, "m": 41, "v": 62}, {"x": 1611, "y": 21671, "w": 20, "h": 503, "m": 53, "v": 63}, {"x": 1745, "y": 21691, "w": 20, "h": 484, "m": 57, "v": 63}, {"x": 3458, "y": 21691, "w": 19, "h": 46, "m": 108}, {"x": 2014, "y": 21707, "w": 20, "h": 476, "m": 65, "v": 64}, {"x": 1946, "y": 21708, "w": 21, "h": 476, "m": 63, "v": 64}, {"x": 3425, "y": 21708, "w": 20, "h": 46, "m": 107}, {"x": 2148, "y": 21719, "w": 19, "h": 475, "m": 69, "v": 83}, {"x": 2249, "y": 21720, "w": 19, "h": 466, "m": 72, "v": 83}, {"x": 438, "y": 21743, "w": 20, "h": 55, "m": 18}, {"x": 3558, "y": 21781, "w": 20, "h": 54, "m": 111}, {"x": 3389, "y": 21895, "w": 21, "h": 45, "m": 106}, {"x": 469, "y": 22055, "w": 20, "h": 66, "m": 19}, {"x": 3525, "y": 22101, "w": 20, "h": 55, "m": 110}, {"x": 1206, "y": 22242, "w": 20, "h": 120, "m": 41, "v": 62}, {"x": 1609, "y": 22290, "w": 21, "h": 82, "m": 53, "v": 63}, {"x": 1744, "y": 22290, "w": 21, "h": 83, "m": 57, "v": 63}, {"x": 1945, "y": 22298, "w": 20, "h": 83, "m": 63, "v": 63}, {"x": 2012, "y": 22298, "w": 20, "h": 83, "m": 65, "v": 63}, {"x": 2145, "y": 22310, "w": 21, "h": 83, "m": 69, "v": 87}, {"x": 2246, "y": 22310, "w": 20, "h": 128, "m": 72, "v": 87}, {"x": 1272, "y": 22495, "w": 20, "h": 324, "m": 43, "v": 68}, {"x": 3423, "y": 22512, "w": 19, "h": 55, "m": 107}, {"x": 1676, "y": 22515, "w": 20, "h": 307, "m": 55, "v": 68}, {"x": 1910, "y": 22550, "w": 20, "h": 280, "m": 62, "v": 69}, {"x": 1776, "y": 22551, "w": 21, "h": 271, "m": 58, "v": 69}, {"x": 435, "y": 22552, "w": 20, "h": 55, "m": 18}, {"x": 2078, "y": 22552, "w": 20, "h": 280, "m": 67, "v": 90}, {"x": 2177, "y": 22552, "w": 21, "h": 280, "m": 70, "v": 90}, {"x": 3556, "y": 22575, "w": 19, "h": 74, "m": 111}, {"x": 3388, "y": 22737, "w": 20, "h": 73, "m": 106}, {"x": 468, "y": 22796, "w": 21, "h": 54, "m": 19}, {"x": 3524, "y": 22826, "w": 20, "h": 46, "m": 110}, {"x": 1138, "y": 22854, "w": 21, "h": 299, "m": 39, "v": 65}, {"x": 1540, "y": 22891, "w": 20, "h": 280, "m": 51, "v": 66}, {"x": 3422, "y": 22906, "w": 20, "h": 63, "m": 107}, {"x": 1943, "y": 22954, "w": 21, "h": 272, "m": 63, "v": 67}, {"x": 1674, "y": 22955, "w": 20, "h": 226, "m": 55, "v": 67}, {"x": 1842, "y": 22955, "w": 21, "h": 263, "m": 60, "v": 67}, {"x": 2077, "y": 22955, "w": 20, "h": 253, "m": 67, "v": 87}, {"x": 2245, "y": 22965, "w": 21, "h": 235, "m": 72, "v": 87}, {"x": 434, "y": 22975, "w": 21, "h": 55, "m": 18}, {"x": 3555, "y": 23004, "w": 20, "h": 47, "m": 111}, {"x": 3387, "y": 23094, "w": 20, "h": 46, "m": 106}, {"x": 1741, "y": 23206, "w": 21, "h": 111, "m": 57, "v": 62}, {"x": 467, "y": 23309, "w": 20, "h": 64, "m": 19}, {"x": 3521, "y": 23338, "w": 21, "h": 54, "m": 110}, {"x": 1104, "y": 23412, "w": 21, "h": 307, "m": 38, "v": 62}, {"x": 1507, "y": 23431, "w": 19, "h": 288, "m": 50, "v": 62}, {"x": 3421, "y": 23436, "w": 19, "h": 63, "m": 107}, {"x": 1909, "y": 23468, "w": 20, "h": 261, "m": 62, "v": 63}, {"x": 2076, "y": 23486, "w": 20, "h": 253, "m": 67, "v": 84}, {"x": 2176, "y": 23486, "w": 20, "h": 254, "m": 70, "v": 84}, {"x": 2311, "y": 23487, "w": 19, "h": 288, "m": 74, "v": 84}, {"x": 434, "y": 23515, "w": 20, "h": 55, "m": 18}, {"x": 3554, "y": 23534, "w": 20, "h": 56, "m": 111}, {"x": 3387, "y": 23606, "w": 19, "h": 56, "m": 106}, {"x": 1105, "y": 23887, "w": 19, "h": 538, "m": 38, "v": 55}, {"x": 1507, "y": 23931, "w": 20, "h": 532, "m": 50, "v": 54}, {"x": 3421, "y": 23937, "w": 20, "h": 72, "m": 107}, {"x": 1909, "y": 23951, "w": 20, "h": 593, "m": 62, "v": 54}, {"x": 2043, "y": 23959, "w": 20, "h": 611, "m": 66, "v": 54}, {"x": 2143, "y": 23960, "w": 20, "h": 621, "m": 69, "v": 75}, {"x": 2311, "y": 23961, "w": 20, "h": 674, "m": 74, "v": 75}, {"x": 466, "y": 24123, "w": 20, "h": 66, "m": 19}, {"x": 3522, "y": 24153, "w": 20, "h": 54, "m": 110}, {"x": 3387, "y": 24322, "w": 19, "h": 54, "m": 106}, {"x": 3421, "y": 24645, "w": 19, "h": 63, "m": 107}, {"x": 1269, "y": 24747, "w": 20, "h": 234, "m": 43, "v": 65}, {"x": 1673, "y": 24757, "w": 20, "h": 217, "m": 55, "v": 65}, {"x": 1808, "y": 24757, "w": 19, "h": 234, "m": 59, "v": 65}, {"x": 2009, "y": 24757, "w": 20, "h": 235, "m": 65, "v": 65}, {"x": 2076, "y": 24758, "w": 19, "h": 225, "m": 67, "v": 75}, {"x": 433, "y": 24762, "w": 19, "h": 63, "m": 18}, {"x": 2209, "y": 24767, "w": 21, "h": 225, "m": 71, "v": 75}, {"x": 2310, "y": 24777, "w": 20, "h": 225, "m": 74, "v": 75}, {"x": 3386, "y": 24860, "w": 20, "h": 64, "m": 106}, {"x": 465, "y": 24923, "w": 20, "h": 55, "m": 19}, {"x": 1437, "y": 25153, "w": 20, "h": 335, "m": 48, "v": 67}, {"x": 3419, "y": 25182, "w": 20, "h": 55, "m": 107}, {"x": 1671, "y": 25189, "w": 20, "h": 307, "m": 55, "v": 68}, {"x": 1940, "y": 25206, "w": 21, "h": 290, "m": 63, "v": 68}, {"x": 1840, "y": 25217, "w": 19, "h": 289, "m": 60, "v": 68}, {"x": 2074, "y": 25225, "w": 20, "h": 271, "m": 67, "v": 75}, {"x": 2242, "y": 25225, "w": 20, "h": 272, "m": 72, "v": 75}, {"x": 2341, "y": 25226, "w": 21, "h": 279, "m": 75, "v": 75}, {"x": 432, "y": 25238, "w": 19, "h": 64, "m": 18}, {"x": 3552, "y": 25265, "w": 20, "h": 62, "m": 111}, {"x": 3383, "y": 25435, "w": 20, "h": 55, "m": 106}, {"x": 465, "y": 25499, "w": 20, "h": 46, "m": 19}, {"x": 3519, "y": 25524, "w": 20, "h": 46, "m": 110}, {"x": 1201, "y": 25619, "w": 22, "h": 332, "m": 41, "v": 66}, {"x": 1605, "y": 25647, "w": 20, "h": 304, "m": 53, "v": 66}, {"x": 1940, "y": 25654, "w": 21, "h": 279, "m": 63, "v": 66}, {"x": 2007, "y": 25655, "w": 21, "h": 296, "m": 65, "v": 66}, {"x": 2242, "y": 25656, "w": 20, "h": 316, "m": 72, "v": 72}, {"x": 3418, "y": 25658, "w": 21, "h": 66, "m": 107}, {"x": 2141, "y": 25666, "w": 21, "h": 278, "m": 69, "v": 72}, {"x": 432, "y": 25679, "w": 19, "h": 55, "m": 18}, {"x": 3551, "y": 25688, "w": 21, "h": 54, "m": 111}, {"x": 3383, "y": 25874, "w": 21, "h": 73, "m": 106}, {"x": 464, "y": 25945, "w": 21, "h": 47, "m": 19}, {"x": 3519, "y": 25955, "w": 20, "h": 56, "m": 110}, {"x": 1371, "y": 26005, "w": 20, "h": 297, "m": 46, "v": 62}, {"x": 1605, "y": 26032, "w": 21, "h": 289, "m": 53, "v": 63}, {"x": 3419, "y": 26045, "w": 20, "h": 65, "m": 107}, {"x": 1772, "y": 26051, "w": 20, "h": 279, "m": 58, "v": 63}, {"x": 2007, "y": 26076, "w": 21, "h": 236, "m": 65, "v": 64}, {"x": 1906, "y": 26077, "w": 20, "h": 234, "m": 62, "v": 64}, {"x": 2309, "y": 26087, "w": 20, "h": 245, "m": 74, "v": 69}, {"x": 2174, "y": 26088, "w": 20, "h": 234, "m": 70, "v": 70}, {"x": 432, "y": 26107, "w": 19, "h": 56, "m": 18}, {"x": 3552, "y": 26127, "w": 20, "h": 73, "m": 111}, {"x": 3384, "y": 26306, "w": 19, "h": 54, "m": 106}, {"x": 464, "y": 26366, "w": 20, "h": 56, "m": 19}, {"x": 3519, "y": 26404, "w": 20, "h": 36, "m": 110}, {"x": 1268, "y": 26442, "w": 20, "h": 359, "m": 43, "v": 60}, {"x": 1671, "y": 26480, "w": 20, "h": 323, "m": 55, "v": 61}, {"x": 1974, "y": 26525, "w": 20, "h": 269, "m": 64, "v": 62}, {"x": 2242, "y": 26525, "w": 19, "h": 342, "m": 72, "v": 67}, {"x": 1839, "y": 26535, "w": 20, "h": 368, "m": 60, "v": 62}, {"x": 3418, "y": 26537, "w": 20, "h": 56, "m": 107}, {"x": 431, "y": 26546, "w": 20, "h": 46, "m": 18}, {"x": 3551, "y": 26566, "w": 20, "h": 63, "m": 111}, {"x": 3383, "y": 26762, "w": 20, "h": 45, "m": 106}, {"x": 2173, "y": 26785, "w": 20, "h": 127, "m": 70, "v": 62}, {"x": 463, "y": 26849, "w": 20, "h": 56, "m": 19}, {"x": 3517, "y": 26887, "w": 21, "h": 47, "m": 110}, {"x": 1436, "y": 26891, "w": 19, "h": 971, "m": 48, "v": 56}, {"x": 1669, "y": 26955, "w": 20, "h": 434, "m": 55, "v": 58}, {"x": 1770, "y": 26973, "w": 21, "h": 685, "m": 58, "v": 58}, {"x": 1972, "y": 27043, "w": 20, "h": 811, "m": 64, "v": 60}, {"x": 1838, "y": 27045, "w": 19, "h": 819, "m": 60, "v": 60}, {"x": 2072, "y": 27045, "w": 20, "h": 810, "m": 67, "v": 64}, {"x": 2240, "y": 27045, "w": 20, "h": 1456, "m": 72, "v": 64}, {"x": 3417, "y": 27057, "w": 20, "h": 55, "m": 107}, {"x": 430, "y": 27065, "w": 20, "h": 55, "m": 18}, {"x": 3551, "y": 27084, "w": 19, "h": 55, "m": 111}, {"x": 3381, "y": 27302, "w": 20, "h": 74, "m": 106}, {"x": 463, "y": 27319, "w": 19, "h": 55, "m": 19}, {"x": 429, "y": 27497, "w": 20, "h": 65, "m": 18}, {"x": 1669, "y": 27513, "w": 20, "h": 259, "m": 55, "v": 58}, {"x": 3415, "y": 27517, "w": 21, "h": 55, "m": 107}, {"x": 3382, "y": 27678, "w": 19, "h": 55, "m": 106}, {"x": 3517, "y": 27869, "w": 20, "h": 54, "m": 110}, {"x": 463, "y": 27917, "w": 20, "h": 55, "m": 19}, {"x": 1200, "y": 28065, "w": 20, "h": 459, "m": 41, "v": 52}, {"x": 1603, "y": 28066, "w": 20, "h": 477, "m": 53, "v": 52}, {"x": 1434, "y": 28075, "w": 22, "h": 450, "m": 48, "v": 52}, {"x": 1737, "y": 28076, "w": 20, "h": 460, "m": 57, "v": 52}, {"x": 1838, "y": 28076, "w": 19, "h": 532, "m": 60, "v": 52}, {"x": 2006, "y": 28076, "w": 19, "h": 530, "m": 65, "v": 52}, {"x": 3449, "y": 28119, "w": 20, "h": 171, "m": 108}, {"x": 3417, "y": 28154, "w": 19, "h": 55, "m": 107}, {"x": 532, "y": 28160, "w": 20, "h": 179, "m": 21}, {"x": 3584, "y": 28353, "w": 20, "h": 55, "m": 112}, {"x": 395, "y": 28401, "w": 20, "h": 46, "m": 17}, {"x": 3382, "y": 28416, "w": 19, "h": 55, "m": 106}, {"x": 3549, "y": 28442, "w": 20, "h": 66, "m": 111}, {"x": 498, "y": 28498, "w": 20, "h": 55, "m": 20}, {"x": 429, "y": 28508, "w": 20, "h": 55, "m": 18}, {"x": 3417, "y": 28648, "w": 19, "h": 56, "m": 107}, {"x": 1603, "y": 28731, "w": 20, "h": 476, "m": 53, "v": 62}, {"x": 2005, "y": 28740, "w": 21, "h": 467, "m": 65, "v": 62}, {"x": 462, "y": 28847, "w": 20, "h": 55, "m": 19}, {"x": 3382, "y": 28864, "w": 20, "h": 55, "m": 106}, {"x": 3518, "y": 28881, "w": 19, "h": 56, "m": 110}, {"x": 3416, "y": 29169, "w": 20, "h": 55, "m": 107}, {"x": 1669, "y": 29196, "w": 20, "h": 378, "m": 55, "v": 68}, {"x": 430, "y": 29203, "w": 20, "h": 75, "m": 18}, {"x": 2073, "y": 29216, "w": 19, "h": 360, "m": 67, "v": 87}, {"x": 3550, "y": 29250, "w": 19, "h": 65, "m": 111}, {"x": 3382, "y": 29323, "w": 20, "h": 46, "m": 106}, {"x": 463, "y": 29430, "w": 19, "h": 45, "m": 19}, {"x": 1603, "y": 29645, "w": 20, "h": 439, "m": 53, "v": 68}, {"x": 2006, "y": 29653, "w": 20, "h": 325, "m": 65, "v": 68}, {"x": 3417, "y": 29655, "w": 19, "h": 64, "m": 107}, {"x": 429, "y": 29661, "w": 21, "h": 63, "m": 18}, {"x": 3517, "y": 29782, "w": 20, "h": 63, "m": 110}, {"x": 3382, "y": 29897, "w": 19, "h": 56, "m": 106}, {"x": 462, "y": 29902, "w": 20, "h": 64, "m": 19}, {"x": 3416, "y": 30068, "w": 20, "h": 54, "m": 107}, {"x": 1770, "y": 30083, "w": 20, "h": 307, "m": 58, "v": 67}, {"x": 2172, "y": 30096, "w": 20, "h": 288, "m": 70, "v": 83}, {"x": 429, "y": 30099, "w": 20, "h": 54, "m": 18}, {"x": 3550, "y": 30141, "w": 19, "h": 64, "m": 111}, {"x": 463, "y": 30251, "w": 19, "h": 55, "m": 19}, {"x": 3381, "y": 30294, "w": 20, "h": 63, "m": 106}, {"x": 3517, "y": 30302, "w": 21, "h": 37, "m": 110}, {"x": 531, "y": 30449, "w": 21, "h": 36, "m": 21}, {"x": 1266, "y": 30481, "w": 20, "h": 191, "m": 43, "v": 77}, {"x": 3417, "y": 30482, "w": 20, "h": 46, "m": 107}, {"x": 3449, "y": 30482, "w": 20, "h": 29, "m": 108}, {"x": 1771, "y": 30487, "w": 20, "h": 190, "m": 58, "v": 78}, {"x": 1669, "y": 30496, "w": 20, "h": 180, "m": 55, "v": 80}, {"x": 1905, "y": 30506, "w": 19, "h": 161, "m": 62, "v": 81}, {"x": 2072, "y": 30507, "w": 19, "h": 171, "m": 67, "v": 90}, {"x": 2172, "y": 30508, "w": 20, "h": 162, "m": 70, "v": 90}, {"x": 429, "y": 30511, "w": 20, "h": 55, "m": 18}, {"x": 3550, "y": 30555, "w": 19, "h": 55, "m": 111}, {"x": 3382, "y": 30617, "w": 20, "h": 45, "m": 106}, {"x": 463, "y": 30689, "w": 19, "h": 46, "m": 19}, {"x": 1199, "y": 30698, "w": 20, "h": 64, "m": 41, "v": 77}, {"x": 1603, "y": 30701, "w": 20, "h": 64, "m": 53, "v": 77}, {"x": 3517, "y": 30742, "w": 20, "h": 56, "m": 110}, {"x": 532, "y": 30862, "w": 20, "h": 47, "m": 21}, {"x": 1133, "y": 30887, "w": 20, "h": 452, "m": 39, "v": 85}, {"x": 3450, "y": 30897, "w": 19, "h": 54, "m": 108}, {"x": 1938, "y": 30919, "w": 21, "h": 426, "m": 63, "v": 85}, {"x": 3416, "y": 30922, "w": 21, "h": 65, "m": 107}, {"x": 1535, "y": 30925, "w": 20, "h": 399, "m": 51, "v": 85}, {"x": 1837, "y": 30929, "w": 21, "h": 408, "m": 60, "v": 85}, {"x": 2071, "y": 30930, "w": 21, "h": 408, "m": 67, "v": 90}, {"x": 2240, "y": 30939, "w": 20, "h": 400, "m": 72, "v": 90}, {"x": 429, "y": 30942, "w": 20, "h": 55, "m": 18}, {"x": 3549, "y": 30987, "w": 21, "h": 55, "m": 111}, {"x": 3382, "y": 31194, "w": 20, "h": 72, "m": 106}, {"x": 463, "y": 31330, "w": 20, "h": 63, "m": 19}, {"x": 3518, "y": 31383, "w": 20, "h": 64, "m": 110}, {"x": 1503, "y": 31491, "w": 20, "h": 277, "m": 50, "v": 80}, {"x": 1101, "y": 31506, "w": 20, "h": 251, "m": 38, "v": 80}, {"x": 2006, "y": 31512, "w": 20, "h": 260, "m": 65, "v": 80}, {"x": 2307, "y": 31516, "w": 21, "h": 260, "m": 74, "v": 84}, {"x": 1905, "y": 31521, "w": 21, "h": 242, "m": 62, "v": 80}, {"x": 2072, "y": 31523, "w": 21, "h": 207, "m": 67, "v": 84}, {"x": 3417, "y": 31525, "w": 19, "h": 64, "m": 107}, {"x": 3383, "y": 31712, "w": 19, "h": 63, "m": 106}, {"x": 1034, "y": 31752, "w": 21, "h": 271, "m": 36, "v": 85}, {"x": 3418, "y": 31783, "w": 19, "h": 46, "m": 107}, {"x": 2073, "y": 31791, "w": 20, "h": 270, "m": 67, "v": 90}, {"x": 1436, "y": 31794, "w": 20, "h": 253, "m": 48, "v": 85}, {"x": 1939, "y": 31797, "w": 20, "h": 253, "m": 63, "v": 85}, {"x": 2242, "y": 31800, "w": 19, "h": 254, "m": 72, "v": 90}, {"x": 2341, "y": 31801, "w": 19, "h": 253, "m": 75, "v": 90}, {"x": 430, "y": 31818, "w": 20, "h": 47, "m": 18}, {"x": 3551, "y": 31846, "w": 20, "h": 65, "m": 111}, {"x": 3383, "y": 31989, "w": 21, "h": 47, "m": 106}, {"x": 464, "y": 32008, "w": 20, "h": 64, "m": 19}, {"x": 3518, "y": 32054, "w": 22, "h": 55, "m": 110}, {"x": 365, "y": 32124, "w": 20, "h": 47, "m": 16}, {"x": 3419, "y": 32143, "w": 19, "h": 63, "m": 107}, {"x": 1134, "y": 32213, "w": 21, "h": 287, "m": 39, "v": 85}, {"x": 1537, "y": 32216, "w": 20, "h": 296, "m": 51, "v": 85}, {"x": 1941, "y": 32227, "w": 19, "h": 280, "m": 63, "v": 85}, {"x": 2074, "y": 32230, "w": 20, "h": 278, "m": 67, "v": 89}, {"x": 2242, "y": 32231, "w": 21, "h": 279, "m": 72, "v": 89}, {"x": 1840, "y": 32237, "w": 19, "h": 279, "m": 60, "v": 85}, {"x": 432, "y": 32249, "w": 19, "h": 55, "m": 18}, {"x": 3552, "y": 32291, "w": 19, "h": 51, "m": 111}, {"x": 3384, "y": 32429, "w": 20, "h": 64, "m": 106}, {"x": 465, "y": 32517, "w": 19, "h": 63, "m": 19}, {"x": 1201, "y": 32588, "w": 22, "h": 633, "m": 41, "v": 80}, {"x": 3419, "y": 32624, "w": 21, "h": 65, "m": 107}, {"x": 1605, "y": 32663, "w": 20, "h": 579, "m": 53, "v": 82}, {"x": 3453, "y": 32680, "w": 19, "h": 27, "m": 108}, {"x": 1773, "y": 32683, "w": 20, "h": 570, "m": 58, "v": 83}, {"x": 1907, "y": 32683, "w": 19, "h": 560, "m": 62, "v": 83}, {"x": 2008, "y": 32691, "w": 20, "h": 561, "m": 65, "v": 83}, {"x": 2174, "y": 32694, "w": 21, "h": 561, "m": 70, "v": 84}, {"x": 432, "y": 32703, "w": 20, "h": 65, "m": 18}, {"x": 3553, "y": 32725, "w": 19, "h": 72, "m": 111}, {"x": 3385, "y": 32849, "w": 20, "h": 55, "m": 106}, {"x": 465, "y": 33129, "w": 20, "h": 64, "m": 19}, {"x": 1203, "y": 33301, "w": 20, "h": 136, "m": 41, "v": 77}, {"x": 535, "y": 33302, "w": 21, "h": 29, "m": 21}, {"x": 1607, "y": 33305, "w": 20, "h": 154, "m": 53, "v": 78}, {"x": 502, "y": 33335, "w": 20, "h": 29, "m": 20}, {"x": 1774, "y": 33342, "w": 20, "h": 100, "m": 58, "v": 85}, {"x": 1908, "y": 33342, "w": 20, "h": 91, "m": 62, "v": 85}, {"x": 2009, "y": 33349, "w": 21, "h": 93, "m": 65, "v": 83}, {"x": 3521, "y": 33436, "w": 13, "h": 71, "m": 110}, {"x": 1204, "y": 33585, "w": 20, "h": 359, "m": 41, "v": 81}, {"x": 1607, "y": 33642, "w": 20, "h": 341, "m": 53, "v": 83}, {"x": 2010, "y": 33643, "w": 20, "h": 350, "m": 65, "v": 83}, {"x": 1908, "y": 33652, "w": 21, "h": 332, "m": 62, "v": 83}, {"x": 2176, "y": 33664, "w": 20, "h": 314, "m": 70, "v": 78}, {"x": 3421, "y": 33665, "w": 19, "h": 55, "m": 107}, {"x": 2310, "y": 33666, "w": 20, "h": 330, "m": 74, "v": 78}, {"x": 433, "y": 33674, "w": 20, "h": 56, "m": 18}, {"x": 3554, "y": 33710, "w": 20, "h": 66, "m": 111}, {"x": 3386, "y": 33898, "w": 20, "h": 54, "m": 106}, {"x": 467, "y": 33968, "w": 20, "h": 56, "m": 19}, {"x": 3522, "y": 34122, "w": 19, "h": 54, "m": 110}, {"x": 1204, "y": 34167, "w": 20, "h": 350, "m": 41, "v": 81}, {"x": 1607, "y": 34170, "w": 21, "h": 350, "m": 53, "v": 81}, {"x": 1943, "y": 34172, "w": 19, "h": 359, "m": 63, "v": 81}, {"x": 2011, "y": 34181, "w": 19, "h": 360, "m": 65, "v": 82}, {"x": 2143, "y": 34184, "w": 21, "h": 350, "m": 69, "v": 71}, {"x": 2244, "y": 34185, "w": 21, "h": 340, "m": 72, "v": 71}, {"x": 3421, "y": 34203, "w": 20, "h": 64, "m": 107}, {"x": 434, "y": 34213, "w": 20, "h": 54, "m": 18}, {"x": 3386, "y": 34433, "w": 21, "h": 75, "m": 106}, {"x": 468, "y": 34616, "w": 19, "h": 63, "m": 19}, {"x": 970, "y": 34792, "w": 20, "h": 1232, "m": 34, "v": 77}, {"x": 1205, "y": 34804, "w": 20, "h": 1241, "m": 41, "v": 77}, {"x": 1373, "y": 34806, "w": 20, "h": 1241, "m": 46, "v": 77}, {"x": 1775, "y": 34808, "w": 20, "h": 1340, "m": 58, "v": 77}, {"x": 2011, "y": 34817, "w": 20, "h": 1339, "m": 65, "v": 77}, {"x": 1910, "y": 34818, "w": 19, "h": 1329, "m": 62, "v": 77}, {"x": 2177, "y": 34821, "w": 20, "h": 1436, "m": 70, "v": 86}, {"x": 3422, "y": 34837, "w": 20, "h": 55, "m": 107}, {"x": 435, "y": 34840, "w": 20, "h": 55, "m": 18}, {"x": 3387, "y": 35017, "w": 20, "h": 47, "m": 106}, {"x": 469, "y": 36061, "w": 20, "h": 63, "m": 19}, {"x": 3524, "y": 36114, "w": 20, "h": 56, "m": 110}, {"x": 3423, "y": 36302, "w": 20, "h": 62, "m": 107}, {"x": 1139, "y": 36370, "w": 19, "h": 1109, "m": 39, "v": 56}, {"x": 1541, "y": 36382, "w": 20, "h": 1047, "m": 51, "v": 56}, {"x": 1944, "y": 36429, "w": 20, "h": 1012, "m": 63, "v": 57}, {"x": 1776, "y": 36430, "w": 21, "h": 1010, "m": 58, "v": 57}, {"x": 2078, "y": 36431, "w": 20, "h": 1002, "m": 67, "v": 90}, {"x": 2178, "y": 36450, "w": 20, "h": 993, "m": 70, "v": 90}, {"x": 435, "y": 36460, "w": 20, "h": 47, "m": 18}, {"x": 3556, "y": 36490, "w": 21, "h": 72, "m": 111}, {"x": 3388, "y": 36712, "w": 20, "h": 56, "m": 106}, {"x": 467, "y": 37549, "w": 20, "h": 55, "m": 19}, {"x": 3522, "y": 37585, "w": 20, "h": 54, "m": 110}, {"x": 3422, "y": 37691, "w": 19, "h": 64, "m": 107}, {"x": 970, "y": 37706, "w": 20, "h": 308, "m": 34, "v": 36}, {"x": 1908, "y": 37706, "w": 21, "h": 325, "m": 62, "v": 36}, {"x": 1372, "y": 37712, "w": 22, "h": 307, "m": 46, "v": 36}, {"x": 1775, "y": 37714, "w": 19, "h": 316, "m": 58, "v": 36}, {"x": 2010, "y": 37724, "w": 21, "h": 307, "m": 65, "v": 36}, {"x": 2176, "y": 37726, "w": 20, "h": 299, "m": 70, "v": 67}, {"x": 434, "y": 37746, "w": 20, "h": 74, "m": 18}, {"x": 3554, "y": 37783, "w": 21, "h": 73, "m": 111}, {"x": 3387, "y": 37880, "w": 19, "h": 55, "m": 106}, {"x": 3421, "y": 39658, "w": 21, "h": 63, "m": 107}, {"x": 503, "y": 41657, "w": 20, "h": 47, "m": 20}, {"x": 434, "y": 41658, "w": 20, "h": 47, "m": 18}, {"x": 367, "y": 41659, "w": 21, "h": 46, "m": 16}, {"x": 568, "y": 41659, "w": 22, "h": 46, "m": 22}, {"x": 3422, "y": 41683, "w": 19, "h": 47, "m": 107}, {"x": 3488, "y": 41685, "w": 20, "h": 48, "m": 109}, {"x": 3555, "y": 41686, "w": 19, "h": 46, "m": 111}, {"x": 3621, "y": 41687, "w": 28, "h": 47, "m": 113}, {"x": 467, "y": 41821, "w": 20, "h": 63, "m": 19}, {"x": 3522, "y": 41865, "w": 20, "h": 55, "m": 110}, {"x": 535, "y": 42036, "w": 21, "h": 37, "m": 21}, {"x": 434, "y": 42071, "w": 19, "h": 54, "m": 18}, {"x": 1573, "y": 42074, "w": 19, "h": 207, "m": 52, "v": 45}, {"x": 1976, "y": 42086, "w": 19, "h": 268, "m": 64, "v": 48}, {"x": 3386, "y": 42151, "w": 19, "h": 54, "m": 106}, {"x": 466, "y": 42259, "w": 19, "h": 55, "m": 19}, {"x": 1337, "y": 42439, "w": 21, "h": 742, "m": 45, "v": 48}, {"x": 1571, "y": 42458, "w": 20, "h": 652, "m": 52, "v": 49}, {"x": 1740, "y": 42505, "w": 20, "h": 686, "m": 57, "v": 50}, {"x": 3420, "y": 42517, "w": 19, "h": 54, "m": 107}, {"x": 1975, "y": 42557, "w": 20, "h": 230, "m": 64, "v": 51}, {"x": 2142, "y": 42561, "w": 19, "h": 562, "m": 69, "v": 57}, {"x": 3452, "y": 42562, "w": 20, "h": 27, "m": 108}, {"x": 432, "y": 42563, "w": 20, "h": 65, "m": 18}, {"x": 2276, "y": 42570, "w": 19, "h": 263, "m": 73, "v": 60}, {"x": 3553, "y": 42616, "w": 19, "h": 65, "m": 111}, {"x": 3384, "y": 42670, "w": 20, "h": 54, "m": 106}, {"x": 465, "y": 42735, "w": 20, "h": 56, "m": 19}, {"x": 3520, "y": 42769, "w": 19, "h": 64, "m": 110}, {"x": 1906, "y": 42929, "w": 21, "h": 244, "m": 62, "v": 52}, {"x": 2041, "y": 42930, "w": 20, "h": 262, "m": 66, "v": 52}, {"x": 432, "y": 42935, "w": 20, "h": 55, "m": 18}, {"x": 2308, "y": 42943, "w": 20, "h": 253, "m": 74, "v": 69}, {"x": 3419, "y": 42957, "w": 19, "h": 48, "m": 107}, {"x": 3552, "y": 42969, "w": 19, "h": 55, "m": 111}, {"x": 465, "y": 43124, "w": 19, "h": 55, "m": 19}, {"x": 3520, "y": 43139, "w": 19, "h": 38, "m": 110}, {"x": 3384, "y": 43148, "w": 20, "h": 72, "m": 106}, {"x": 1337, "y": 43279, "w": 20, "h": 293, "m": 45, "v": 51}, {"x": 3419, "y": 43284, "w": 20, "h": 107, "m": 107}, {"x": 1571, "y": 43289, "w": 20, "h": 278, "m": 52, "v": 51}, {"x": 1740, "y": 43289, "w": 19, "h": 277, "m": 57, "v": 51}, {"x": 1974, "y": 43299, "w": 21, "h": 268, "m": 64, "v": 51}, {"x": 2276, "y": 43312, "w": 19, "h": 284, "m": 73, "v": 69}, {"x": 432, "y": 43313, "w": 20, "h": 45, "m": 18}, {"x": 2142, "y": 43328, "w": 20, "h": 268, "m": 69, "v": 70}, {"x": 3552, "y": 43357, "w": 20, "h": 44, "m": 111}, {"x": 465, "y": 43499, "w": 20, "h": 55, "m": 19}, {"x": 3384, "y": 43531, "w": 20, "h": 55, "m": 106}, {"x": 3520, "y": 43550, "w": 20, "h": 37, "m": 110}, {"x": 1571, "y": 43617, "w": 20, "h": 576, "m": 52, "v": 50}, {"x": 1807, "y": 43644, "w": 19, "h": 504, "m": 59, "v": 51}, {"x": 1974, "y": 43699, "w": 20, "h": 253, "m": 64, "v": 52}, {"x": 2108, "y": 43700, "w": 19, "h": 414, "m": 68, "v": 70}, {"x": 2376, "y": 43711, "w": 21, "h": 388, "m": 76, "v": 70}, {"x": 432, "y": 43722, "w": 19, "h": 37, "m": 18}, {"x": 3419, "y": 43738, "w": 20, "h": 36, "m": 107}, {"x": 3552, "y": 43746, "w": 20, "h": 56, "m": 111}, {"x": 3384, "y": 43909, "w": 20, "h": 45, "m": 106}, {"x": 1974, "y": 44022, "w": 21, "h": 110, "m": 64, "v": 45}, {"x": 2276, "y": 44035, "w": 19, "h": 127, "m": 73, "v": 64}, {"x": 465, "y": 44207, "w": 21, "h": 54, "m": 19}, {"x": 3520, "y": 44259, "w": 20, "h": 38, "m": 110}, {"x": 1571, "y": 44359, "w": 20, "h": 254, "m": 52, "v": 45}, {"x": 1906, "y": 44369, "w": 20, "h": 245, "m": 62, "v": 45}, {"x": 1974, "y": 44369, "w": 20, "h": 237, "m": 64, "v": 45}, {"x": 2107, "y": 44371, "w": 21, "h": 245, "m": 68, "v": 61}, {"x": 2209, "y": 44380, "w": 19, "h": 236, "m": 71, "v": 61}, {"x": 431, "y": 44383, "w": 20, "h": 47, "m": 18}, {"x": 3419, "y": 44389, "w": 20, "h": 48, "m": 107}, {"x": 3553, "y": 44418, "w": 20, "h": 56, "m": 111}, {"x": 3384, "y": 44525, "w": 20, "h": 55, "m": 106}, {"x": 465, "y": 44556, "w": 20, "h": 54, "m": 19}, {"x": 3520, "y": 44607, "w": 20, "h": 45, "m": 110}, {"x": 1237, "y": 44708, "w": 20, "h": 335, "m": 42, "v": 45}, {"x": 2040, "y": 44722, "w": 21, "h": 434, "m": 66, "v": 45}, {"x": 1637, "y": 44730, "w": 20, "h": 317, "m": 54, "v": 45}, {"x": 432, "y": 44736, "w": 19, "h": 46, "m": 18}, {"x": 1873, "y": 44739, "w": 21, "h": 290, "m": 61, "v": 45}, {"x": 2142, "y": 44741, "w": 19, "h": 390, "m": 69, "v": 61}, {"x": 3419, "y": 44768, "w": 19, "h": 47, "m": 107}, {"x": 3553, "y": 44769, "w": 19, "h": 56, "m": 111}, {"x": 3384, "y": 44957, "w": 19, "h": 56, "m": 106}, {"x": 465, "y": 44961, "w": 19, "h": 64, "m": 19}, {"x": 3519, "y": 45003, "w": 20, "h": 56, "m": 110}, {"x": 1000, "y": 45092, "w": 21, "h": 263, "m": 35, "v": 43}, {"x": 1403, "y": 45097, "w": 20, "h": 272, "m": 47, "v": 43}, {"x": 1906, "y": 45119, "w": 20, "h": 252, "m": 62, "v": 44}, {"x": 2208, "y": 45119, "w": 21, "h": 254, "m": 71, "v": 59}, {"x": 432, "y": 45123, "w": 19, "h": 46, "m": 18}, {"x": 3419, "y": 45139, "w": 19, "h": 63, "m": 107}, {"x": 3552, "y": 45158, "w": 20, "h": 54, "m": 111}, {"x": 3384, "y": 45327, "w": 20, "h": 47, "m": 106}, {"x": 464, "y": 45411, "w": 21, "h": 37, "m": 19}, {"x": 533, "y": 45420, "w": 20, "h": 29, "m": 21}, {"x": 1101, "y": 45427, "w": 21, "h": 244, "m": 38, "v": 39}, {"x": 1505, "y": 45438, "w": 20, "h": 236, "m": 50, "v": 42}, {"x": 1906, "y": 45451, "w": 20, "h": 242, "m": 62, "v": 45}, {"x": 1806, "y": 45458, "w": 20, "h": 235, "m": 59, "v": 47}, {"x": 2040, "y": 45460, "w": 20, "h": 323, "m": 66, "v": 48}, {"x": 3419, "y": 45470, "w": 19, "h": 54, "m": 107}, {"x": 3519, "y": 45471, "w": 21, "h": 45, "m": 110}, {"x": 501, "y": 45482, "w": 19, "h": 18, "m": 20}, {"x": 3384, "y": 45593, "w": 20, "h": 57, "m": 106}, {"x": 3418, "y": 45755, "w": 21, "h": 55, "m": 107}, {"x": 1169, "y": 45777, "w": 21, "h": 225, "m": 40, "v": 47}, {"x": 1571, "y": 45789, "w": 19, "h": 252, "m": 52, "v": 47}, {"x": 1805, "y": 45789, "w": 21, "h": 261, "m": 59, "v": 47}, {"x": 1906, "y": 45808, "w": 20, "h": 242, "m": 62, "v": 48}, {"x": 2141, "y": 45810, "w": 20, "h": 251, "m": 69, "v": 60}, {"x": 432, "y": 45813, "w": 19, "h": 56, "m": 18}, {"x": 3553, "y": 45855, "w": 19, "h": 55, "m": 111}, {"x": 3385, "y": 45961, "w": 19, "h": 55, "m": 106}, {"x": 1806, "y": 46181, "w": 20, "h": 208, "m": 59, "v": 39}, {"x": 1170, "y": 46188, "w": 20, "h": 198, "m": 40, "v": 39}, {"x": 1906, "y": 46190, "w": 21, "h": 199, "m": 62, "v": 39}, {"x": 1974, "y": 46191, "w": 20, "h": 199, "m": 64, "v": 39}, {"x": 1571, "y": 46199, "w": 20, "h": 189, "m": 52, "v": 39}, {"x": 2107, "y": 46211, "w": 21, "h": 179, "m": 68, "v": 53}, {"x": 3420, "y": 46211, "w": 19, "h": 54, "m": 107}, {"x": 3384, "y": 46318, "w": 21, "h": 54, "m": 106}, {"x": 465, "y": 46332, "w": 19, "h": 64, "m": 19}, {"x": 3419, "y": 46480, "w": 20, "h": 45, "m": 107}, {"x": 535, "y": 46485, "w": 19, "h": 38, "m": 21}, {"x": 1237, "y": 46485, "w": 20, "h": 282, "m": 42, "v": 39}, {"x": 1637, "y": 46496, "w": 21, "h": 274, "m": 54, "v": 42}, {"x": 1739, "y": 46524, "w": 21, "h": 245, "m": 57, "v": 49}, {"x": 2041, "y": 46534, "w": 19, "h": 236, "m": 66, "v": 52}, {"x": 1907, "y": 46542, "w": 19, "h": 228, "m": 62, "v": 53}, {"x": 500, "y": 46549, "w": 21, "h": 27, "m": 20}, {"x": 3385, "y": 46687, "w": 20, "h": 74, "m": 106}, {"x": 536, "y": 46838, "w": 20, "h": 46, "m": 21}, {"x": 1305, "y": 46838, "w": 19, "h": 305, "m": 44, "v": 49}, {"x": 3420, "y": 46840, "w": 20, "h": 55, "m": 107}, {"x": 1705, "y": 46857, "w": 20, "h": 288, "m": 56, "v": 54}, {"x": 1807, "y": 46884, "w": 21, "h": 280, "m": 59, "v": 61}, {"x": 1908, "y": 46885, "w": 19, "h": 379, "m": 62, "v": 61}, {"x": 1975, "y": 46885, "w": 20, "h": 568, "m": 64, "v": 61}, {"x": 501, "y": 46900, "w": 21, "h": 47, "m": 20}, {"x": 3386, "y": 47084, "w": 20, "h": 54, "m": 106}, {"x": 3422, "y": 47201, "w": 19, "h": 63, "m": 107}, {"x": 434, "y": 47206, "w": 20, "h": 46, "m": 18}, {"x": 1339, "y": 47215, "w": 20, "h": 263, "m": 45, "v": 54}, {"x": 1742, "y": 47225, "w": 20, "h": 263, "m": 57, "v": 54}, {"x": 1875, "y": 47226, "w": 20, "h": 289, "m": 61, "v": 54}, {"x": 3522, "y": 47363, "w": 20, "h": 55, "m": 110}, {"x": 467, "y": 47377, "w": 20, "h": 64, "m": 19}, {"x": 3387, "y": 47380, "w": 20, "h": 55, "m": 106}, {"x": 536, "y": 47520, "w": 20, "h": 37, "m": 21}, {"x": 1706, "y": 47521, "w": 21, "h": 289, "m": 56, "v": 54}, {"x": 1305, "y": 47528, "w": 21, "h": 290, "m": 44, "v": 56}, {"x": 1977, "y": 47547, "w": 21, "h": 264, "m": 64, "v": 61}, {"x": 1809, "y": 47556, "w": 19, "h": 272, "m": 59, "v": 63}, {"x": 3422, "y": 47567, "w": 20, "h": 46, "m": 107}, {"x": 503, "y": 47573, "w": 21, "h": 28, "m": 20}, {"x": 3387, "y": 47766, "w": 20, "h": 63, "m": 106}, {"x": 1240, "y": 47825, "w": 20, "h": 651, "m": 42, "v": 62}, {"x": 1640, "y": 47880, "w": 20, "h": 590, "m": 54, "v": 63}, {"x": 1743, "y": 47908, "w": 19, "h": 242, "m": 57, "v": 64}, {"x": 3422, "y": 47908, "w": 20, "h": 55, "m": 107}, {"x": 3455, "y": 47908, "w": 19, "h": 37, "m": 108}, {"x": 1877, "y": 47917, "w": 20, "h": 561, "m": 61, "v": 64}, {"x": 2044, "y": 47917, "w": 20, "h": 561, "m": 66, "v": 64}, {"x": 2144, "y": 47927, "w": 21, "h": 233, "m": 69, "v": 53}, {"x": 435, "y": 47932, "w": 20, "h": 72, "m": 18}, {"x": 3556, "y": 47945, "w": 19, "h": 71, "m": 111}, {"x": 3523, "y": 48078, "w": 20, "h": 37, "m": 110}, {"x": 3387, "y": 48104, "w": 20, "h": 72, "m": 106}, {"x": 468, "y": 48138, "w": 19, "h": 45, "m": 19}, {"x": 2212, "y": 48264, "w": 19, "h": 233, "m": 71, "v": 62}, {"x": 3422, "y": 48274, "w": 21, "h": 51, "m": 107}, {"x": 3556, "y": 48290, "w": 19, "h": 54, "m": 111}, {"x": 3523, "y": 48397, "w": 20, "h": 45, "m": 110}, {"x": 3387, "y": 48404, "w": 21, "h": 56, "m": 106}, {"x": 1240, "y": 48557, "w": 20, "h": 299, "m": 42, "v": 69}, {"x": 1640, "y": 48577, "w": 21, "h": 237, "m": 54, "v": 70}, {"x": 1877, "y": 48577, "w": 19, "h": 281, "m": 61, "v": 70}, {"x": 2044, "y": 48577, "w": 20, "h": 281, "m": 66, "v": 70}, {"x": 2145, "y": 48578, "w": 20, "h": 292, "m": 69, "v": 65}, {"x": 436, "y": 48586, "w": 19, "h": 46, "m": 18}, {"x": 2279, "y": 48587, "w": 19, "h": 272, "m": 73, "v": 65}, {"x": 3422, "y": 48601, "w": 20, "h": 55, "m": 107}, {"x": 469, "y": 48750, "w": 19, "h": 62, "m": 19}, {"x": 3388, "y": 48784, "w": 19, "h": 63, "m": 106}, {"x": 1407, "y": 48846, "w": 21, "h": 719, "m": 47, "v": 68}, {"x": 1641, "y": 48892, "w": 20, "h": 674, "m": 54, "v": 69}, {"x": 1978, "y": 48956, "w": 21, "h": 469, "m": 64, "v": 70}, {"x": 2045, "y": 48966, "w": 20, "h": 609, "m": 66, "v": 70}, {"x": 2212, "y": 48975, "w": 21, "h": 592, "m": 71, "v": 74}, {"x": 436, "y": 48991, "w": 21, "h": 55, "m": 18}, {"x": 3423, "y": 48999, "w": 20, "h": 46, "m": 107}, {"x": 3557, "y": 49019, "w": 19, "h": 54, "m": 111}, {"x": 1945, "y": 49368, "w": 21, "h": 207, "m": 63, "v": 61}, {"x": 3390, "y": 49509, "w": 20, "h": 47, "m": 106}, {"x": 471, "y": 49565, "w": 20, "h": 55, "m": 19}, {"x": 3526, "y": 49592, "w": 19, "h": 54, "m": 110}, {"x": 1409, "y": 49680, "w": 21, "h": 252, "m": 47, "v": 59}, {"x": 1644, "y": 49690, "w": 20, "h": 243, "m": 54, "v": 59}, {"x": 1812, "y": 49690, "w": 20, "h": 251, "m": 59, "v": 59}, {"x": 1745, "y": 49691, "w": 20, "h": 233, "m": 57, "v": 59}, {"x": 437, "y": 49699, "w": 20, "h": 55, "m": 18}, {"x": 1946, "y": 49699, "w": 21, "h": 243, "m": 63, "v": 59}, {"x": 2047, "y": 49700, "w": 19, "h": 233, "m": 66, "v": 59}, {"x": 2148, "y": 49701, "w": 19, "h": 252, "m": 69, "v": 64}, {"x": 3425, "y": 49717, "w": 19, "h": 45, "m": 107}, {"x": 3558, "y": 49726, "w": 20, "h": 64, "m": 111}, {"x": 3390, "y": 49885, "w": 20, "h": 65, "m": 106}, {"x": 471, "y": 49994, "w": 20, "h": 63, "m": 19}, {"x": 3526, "y": 50011, "w": 20, "h": 55, "m": 110}, {"x": 1176, "y": 50080, "w": 20, "h": 426, "m": 40, "v": 54}, {"x": 1410, "y": 50082, "w": 20, "h": 451, "m": 47, "v": 54}, {"x": 1711, "y": 50083, "w": 19, "h": 507, "m": 56, "v": 54}, {"x": 1980, "y": 50083, "w": 21, "h": 515, "m": 64, "v": 54}, {"x": 1578, "y": 50092, "w": 19, "h": 442, "m": 52, "v": 55}, {"x": 1813, "y": 50092, "w": 20, "h": 506, "m": 59, "v": 55}, {"x": 2114, "y": 50094, "w": 20, "h": 505, "m": 68, "v": 60}, {"x": 3426, "y": 50100, "w": 20, "h": 55, "m": 107}, {"x": 439, "y": 50101, "w": 19, "h": 55, "m": 18}, {"x": 3559, "y": 50137, "w": 20, "h": 55, "m": 111}, {"x": 3391, "y": 50325, "w": 20, "h": 44, "m": 106}, {"x": 472, "y": 50469, "w": 19, "h": 66, "m": 19}, {"x": 3426, "y": 50710, "w": 19, "h": 46, "m": 107}, {"x": 1311, "y": 50746, "w": 19, "h": 225, "m": 44, "v": 53}, {"x": 541, "y": 50748, "w": 20, "h": 19, "m": 21}, {"x": 1711, "y": 50748, "w": 21, "h": 235, "m": 56, "v": 53}, {"x": 1813, "y": 50783, "w": 20, "h": 217, "m": 59, "v": 61}, {"x": 3527, "y": 50790, "w": 19, "h": 57, "m": 110}, {"x": 438, "y": 50793, "w": 21, "h": 63, "m": 18}, {"x": 1982, "y": 50793, "w": 20, "h": 191, "m": 64, "v": 61}, {"x": 3392, "y": 50863, "w": 19, "h": 56, "m": 106}, {"x": 472, "y": 50919, "w": 19, "h": 63, "m": 19}, {"x": 1344, "y": 51078, "w": 20, "h": 612, "m": 45, "v": 62}, {"x": 1578, "y": 51098, "w": 20, "h": 594, "m": 52, "v": 63}, {"x": 1747, "y": 51143, "w": 20, "h": 549, "m": 57, "v": 64}, {"x": 1880, "y": 51143, "w": 21, "h": 245, "m": 61, "v": 64}, {"x": 3459, "y": 51143, "w": 20, "h": 46, "m": 108}, {"x": 1982, "y": 51153, "w": 20, "h": 235, "m": 64, "v": 64}, {"x": 2149, "y": 51154, "w": 20, "h": 245, "m": 69, "v": 56}, {"x": 3426, "y": 51169, "w": 20, "h": 46, "m": 107}, {"x": 2282, "y": 51172, "w": 20, "h": 236, "m": 73, "v": 61}, {"x": 439, "y": 51197, "w": 20, "h": 55, "m": 18}, {"x": 3560, "y": 51197, "w": 20, "h": 55, "m": 111}, {"x": 3527, "y": 51323, "w": 20, "h": 45, "m": 110}, {"x": 472, "y": 51341, "w": 20, "h": 56, "m": 19}, {"x": 3392, "y": 51358, "w": 19, "h": 47, "m": 106}, {"x": 2048, "y": 51487, "w": 20, "h": 205, "m": 66, "v": 65}, {"x": 440, "y": 51494, "w": 19, "h": 54, "m": 18}, {"x": 2317, "y": 51498, "w": 20, "h": 205, "m": 74, "v": 70}, {"x": 3427, "y": 51502, "w": 19, "h": 37, "m": 107}, {"x": 3560, "y": 51529, "w": 20, "h": 65, "m": 111}, {"x": 3392, "y": 51618, "w": 20, "h": 29, "m": 106}, {"x": 473, "y": 51644, "w": 19, "h": 65, "m": 19}, {"x": 3528, "y": 51654, "w": 19, "h": 46, "m": 110}, {"x": 1345, "y": 51788, "w": 20, "h": 349, "m": 45, "v": 65}, {"x": 1579, "y": 51807, "w": 20, "h": 207, "m": 52, "v": 66}, {"x": 1747, "y": 51825, "w": 21, "h": 278, "m": 57, "v": 66}, {"x": 440, "y": 51833, "w": 20, "h": 55, "m": 18}, {"x": 1881, "y": 51834, "w": 20, "h": 269, "m": 61, "v": 66}, {"x": 1983, "y": 51834, "w": 19, "h": 270, "m": 64, "v": 66}, {"x": 2149, "y": 51836, "w": 21, "h": 262, "m": 69, "v": 72}, {"x": 2283, "y": 51845, "w": 20, "h": 269, "m": 73, "v": 72}, {"x": 3427, "y": 51850, "w": 20, "h": 56, "m": 107}, {"x": 3560, "y": 51870, "w": 20, "h": 73, "m": 111}, {"x": 474, "y": 51966, "w": 19, "h": 46, "m": 19}, {"x": 3528, "y": 51995, "w": 20, "h": 46, "m": 110}, {"x": 3392, "y": 52040, "w": 20, "h": 63, "m": 106}, {"x": 1580, "y": 52128, "w": 19, "h": 613, "m": 52, "v": 67}, {"x": 1814, "y": 52136, "w": 21, "h": 542, "m": 59, "v": 67}, {"x": 2116, "y": 52175, "w": 21, "h": 470, "m": 68, "v": 74}, {"x": 3428, "y": 52183, "w": 20, "h": 54, "m": 107}, {"x": 2384, "y": 52185, "w": 21, "h": 552, "m": 76, "v": 74}, {"x": 440, "y": 52190, "w": 20, "h": 54, "m": 18}, {"x": 3561, "y": 52220, "w": 20, "h": 72, "m": 111}, {"x": 474, "y": 52405, "w": 19, "h": 46, "m": 19}, {"x": 3528, "y": 52436, "w": 21, "h": 45, "m": 110}, {"x": 1983, "y": 52524, "w": 20, "h": 210, "m": 64, "v": 66}, {"x": 441, "y": 52539, "w": 20, "h": 56, "m": 18}, {"x": 2284, "y": 52544, "w": 19, "h": 200, "m": 73, "v": 72}, {"x": 3561, "y": 52570, "w": 19, "h": 65, "m": 111}, {"x": 3392, "y": 52660, "w": 21, "h": 56, "m": 106}, {"x": 474, "y": 52676, "w": 20, "h": 55, "m": 19}, {"x": 3528, "y": 52714, "w": 20, "h": 47, "m": 110}, {"x": 3428, "y": 52840, "w": 19, "h": 55, "m": 107}, {"x": 1179, "y": 52843, "w": 20, "h": 270, "m": 40, "v": 67}, {"x": 1580, "y": 52847, "w": 20, "h": 271, "m": 52, "v": 67}, {"x": 2217, "y": 52860, "w": 21, "h": 269, "m": 71, "v": 73}, {"x": 1915, "y": 52867, "w": 20, "h": 260, "m": 62, "v": 68}, {"x": 2117, "y": 52868, "w": 19, "h": 260, "m": 68, "v": 73}, {"x": 441, "y": 52872, "w": 20, "h": 56, "m": 18}, {"x": 3562, "y": 52905, "w": 19, "h": 55, "m": 111}, {"x": 474, "y": 53042, "w": 20, "h": 45, "m": 19}, {"x": 3393, "y": 53055, "w": 21, "h": 75, "m": 106}, {"x": 3529, "y": 53074, "w": 21, "h": 56, "m": 110}, {"x": 1246, "y": 53149, "w": 20, "h": 342, "m": 42, "v": 66}, {"x": 1647, "y": 53187, "w": 20, "h": 307, "m": 54, "v": 67}, {"x": 1882, "y": 53206, "w": 20, "h": 288, "m": 61, "v": 68}, {"x": 3429, "y": 53208, "w": 19, "h": 46, "m": 107}, {"x": 441, "y": 53211, "w": 20, "h": 46, "m": 18}, {"x": 2050, "y": 53215, "w": 20, "h": 316, "m": 66, "v": 68}, {"x": 2151, "y": 53217, "w": 20, "h": 336, "m": 69, "v": 74}, {"x": 3561, "y": 53246, "w": 21, "h": 65, "m": 111}, {"x": 474, "y": 53391, "w": 20, "h": 55, "m": 19}, {"x": 3394, "y": 53407, "w": 20, "h": 54, "m": 106}, {"x": 3529, "y": 53425, "w": 20, "h": 47, "m": 110}, {"x": 1011, "y": 53512, "w": 20, "h": 280, "m": 35, "v": 66}, {"x": 1413, "y": 53527, "w": 20, "h": 261, "m": 47, "v": 67}, {"x": 3429, "y": 53531, "w": 19, "h": 65, "m": 107}, {"x": 2218, "y": 53541, "w": 20, "h": 260, "m": 71, "v": 73}, {"x": 441, "y": 53542, "w": 20, "h": 56, "m": 18}, {"x": 1916, "y": 53548, "w": 20, "h": 243, "m": 62, "v": 67}, {"x": 3562, "y": 53570, "w": 19, "h": 54, "m": 111}, {"x": 474, "y": 53686, "w": 20, "h": 55, "m": 19}, {"x": 3393, "y": 53729, "w": 21, "h": 64, "m": 106}, {"x": 1111, "y": 53821, "w": 20, "h": 313, "m": 38, "v": 67}, {"x": 1514, "y": 53824, "w": 20, "h": 313, "m": 50, "v": 67}, {"x": 3429, "y": 53827, "w": 18, "h": 56, "m": 107}, {"x": 1815, "y": 53861, "w": 20, "h": 286, "m": 59, "v": 68}, {"x": 1915, "y": 53870, "w": 20, "h": 241, "m": 62, "v": 68}, {"x": 2050, "y": 53871, "w": 19, "h": 305, "m": 66, "v": 68}, {"x": 3528, "y": 53891, "w": 20, "h": 54, "m": 110}, {"x": 3393, "y": 54060, "w": 20, "h": 63, "m": 106}, {"x": 3428, "y": 54168, "w": 19, "h": 53, "m": 107}, {"x": 1178, "y": 54178, "w": 20, "h": 289, "m": 40, "v": 70}, {"x": 1580, "y": 54199, "w": 19, "h": 271, "m": 52, "v": 70}, {"x": 1915, "y": 54209, "w": 20, "h": 254, "m": 62, "v": 70}, {"x": 1815, "y": 54217, "w": 19, "h": 263, "m": 59, "v": 70}, {"x": 2149, "y": 54229, "w": 21, "h": 237, "m": 69, "v": 74}, {"x": 440, "y": 54232, "w": 20, "h": 55, "m": 18}, {"x": 3561, "y": 54248, "w": 20, "h": 73, "m": 111}, {"x": 3393, "y": 54400, "w": 19, "h": 55, "m": 106}, {"x": 1580, "y": 54541, "w": 19, "h": 201, "m": 52, "v": 63}, {"x": 1178, "y": 54547, "w": 20, "h": 192, "m": 40, "v": 62}, {"x": 1914, "y": 54551, "w": 20, "h": 192, "m": 62, "v": 62}, {"x": 1814, "y": 54559, "w": 20, "h": 200, "m": 59, "v": 62}, {"x": 2115, "y": 54561, "w": 20, "h": 201, "m": 68, "v": 67}, {"x": 3427, "y": 54572, "w": 19, "h": 45, "m": 107}, {"x": 3391, "y": 54689, "w": 21, "h": 37, "m": 106}, {"x": 3426, "y": 54806, "w": 20, "h": 45, "m": 107}, {"x": 473, "y": 54835, "w": 20, "h": 47, "m": 19}, {"x": 542, "y": 54835, "w": 20, "h": 48, "m": 21}, {"x": 1110, "y": 54843, "w": 20, "h": 289, "m": 38, "v": 58}, {"x": 1512, "y": 54844, "w": 21, "h": 290, "m": 50, "v": 58}, {"x": 1711, "y": 54848, "w": 21, "h": 288, "m": 56, "v": 59}, {"x": 1813, "y": 54884, "w": 20, "h": 262, "m": 59, "v": 68}, {"x": 1914, "y": 54893, "w": 20, "h": 235, "m": 62, "v": 71}, {"x": 507, "y": 54897, "w": 20, "h": 28, "m": 20}, {"x": 2048, "y": 54903, "w": 20, "h": 226, "m": 66, "v": 70}, {"x": 3391, "y": 55066, "w": 20, "h": 56, "m": 106}, {"x": 1076, "y": 55183, "w": 20, "h": 485, "m": 37, "v": 67}, {"x": 542, "y": 55194, "w": 19, "h": 38, "m": 21}, {"x": 1479, "y": 55205, "w": 20, "h": 478, "m": 49, "v": 70}, {"x": 3426, "y": 55227, "w": 19, "h": 55, "m": 107}, {"x": 1746, "y": 55243, "w": 20, "h": 539, "m": 57, "v": 80}, {"x": 1982, "y": 55252, "w": 20, "h": 361, "m": 64, "v": 81}, {"x": 1880, "y": 55261, "w": 20, "h": 388, "m": 61, "v": 81}, {"x": 438, "y": 55266, "w": 20, "h": 56, "m": 18}, {"x": 3527, "y": 55364, "w": 20, "h": 66, "m": 110}, {"x": 471, "y": 55404, "w": 21, "h": 53, "m": 19}, {"x": 3391, "y": 55490, "w": 20, "h": 72, "m": 106}, {"x": 2048, "y": 55603, "w": 19, "h": 206, "m": 66, "v": 83}, {"x": 1177, "y": 55919, "w": 19, "h": 297, "m": 40, "v": 85}, {"x": 3459, "y": 55928, "w": 19, "h": 54, "m": 108}, {"x": 1578, "y": 55940, "w": 20, "h": 278, "m": 52, "v": 85}, {"x": 1813, "y": 55940, "w": 20, "h": 288, "m": 59, "v": 85}, {"x": 1913, "y": 55941, "w": 21, "h": 270, "m": 62, "v": 85}, {"x": 2114, "y": 55943, "w": 21, "h": 278, "m": 68, "v": 65}, {"x": 439, "y": 55945, "w": 20, "h": 56, "m": 18}, {"x": 3426, "y": 55952, "w": 20, "h": 47, "m": 107}, {"x": 3559, "y": 55981, "w": 20, "h": 55, "m": 111}, {"x": 472, "y": 56062, "w": 20, "h": 65, "m": 19}, {"x": 3527, "y": 56079, "w": 20, "h": 55, "m": 110}, {"x": 3391, "y": 56140, "w": 20, "h": 64, "m": 106}, {"x": 1244, "y": 56225, "w": 21, "h": 433, "m": 42, "v": 85}, {"x": 1644, "y": 56246, "w": 21, "h": 325, "m": 54, "v": 85}, {"x": 1880, "y": 56282, "w": 20, "h": 308, "m": 61, "v": 85}, {"x": 2048, "y": 56292, "w": 19, "h": 406, "m": 66, "v": 85}, {"x": 439, "y": 56297, "w": 20, "h": 55, "m": 18}, {"x": 2148, "y": 56302, "w": 21, "h": 380, "m": 69, "v": 82}, {"x": 3426, "y": 56302, "w": 20, "h": 36, "m": 107}, {"x": 3560, "y": 56330, "w": 19, "h": 54, "m": 111}, {"x": 472, "y": 56458, "w": 21, "h": 65, "m": 19}, {"x": 3392, "y": 56499, "w": 20, "h": 65, "m": 106}, {"x": 3527, "y": 56508, "w": 20, "h": 56, "m": 110}, {"x": 1480, "y": 56666, "w": 19, "h": 272, "m": 49, "v": 85}, {"x": 1077, "y": 56672, "w": 21, "h": 261, "m": 37, "v": 85}, {"x": 3427, "y": 56679, "w": 19, "h": 37, "m": 107}, {"x": 1982, "y": 56688, "w": 20, "h": 252, "m": 64, "v": 85}, {"x": 440, "y": 56692, "w": 20, "h": 47, "m": 18}, {"x": 2284, "y": 56708, "w": 19, "h": 260, "m": 73, "v": 83}, {"x": 3560, "y": 56726, "w": 20, "h": 55, "m": 111}, {"x": 474, "y": 56872, "w": 19, "h": 55, "m": 19}, {"x": 3392, "y": 56877, "w": 21, "h": 55, "m": 106}, {"x": 3528, "y": 56904, "w": 20, "h": 54, "m": 110}, {"x": 1111, "y": 57030, "w": 20, "h": 262, "m": 38, "v": 84}, {"x": 1916, "y": 57035, "w": 19, "h": 261, "m": 62, "v": 85}, {"x": 1513, "y": 57041, "w": 20, "h": 244, "m": 50, "v": 85}, {"x": 2049, "y": 57044, "w": 20, "h": 244, "m": 66, "v": 85}, {"x": 441, "y": 57049, "w": 19, "h": 55, "m": 18}, {"x": 2218, "y": 57054, "w": 19, "h": 244, "m": 71, "v": 82}, {"x": 3428, "y": 57054, "w": 20, "h": 54, "m": 107}, {"x": 3561, "y": 57090, "w": 20, "h": 55, "m": 111}, {"x": 3393, "y": 57233, "w": 20, "h": 55, "m": 106}, {"x": 1111, "y": 57372, "w": 21, "h": 368, "m": 38, "v": 77}, {"x": 3429, "y": 57377, "w": 19, "h": 45, "m": 107}, {"x": 1514, "y": 57400, "w": 21, "h": 343, "m": 50, "v": 76}, {"x": 474, "y": 57401, "w": 20, "h": 37, "m": 19}, {"x": 544, "y": 57401, "w": 20, "h": 28, "m": 21}, {"x": 1917, "y": 57438, "w": 19, "h": 724, "m": 62, "v": 85}, {"x": 1816, "y": 57439, "w": 20, "h": 750, "m": 59, "v": 85}, {"x": 2051, "y": 57448, "w": 19, "h": 715, "m": 66, "v": 85}, {"x": 510, "y": 57454, "w": 21, "h": 37, "m": 20}, {"x": 3394, "y": 57637, "w": 20, "h": 63, "m": 106}, {"x": 3530, "y": 57673, "w": 20, "h": 64, "m": 110}, {"x": 1011, "y": 57827, "w": 20, "h": 339, "m": 35, "v": 80}, {"x": 1413, "y": 57831, "w": 20, "h": 348, "m": 47, "v": 80}, {"x": 442, "y": 57839, "w": 19, "h": 54, "m": 18}, {"x": 3429, "y": 57877, "w": 20, "h": 45, "m": 107}, {"x": 2151, "y": 57904, "w": 20, "h": 270, "m": 69, "v": 75}, {"x": 3562, "y": 57939, "w": 20, "h": 55, "m": 111}, {"x": 3395, "y": 58099, "w": 19, "h": 56, "m": 106}, {"x": 475, "y": 58106, "w": 20, "h": 56, "m": 19}, {"x": 3529, "y": 58135, "w": 21, "h": 64, "m": 110}, {"x": 3430, "y": 58260, "w": 19, "h": 54, "m": 107}, {"x": 1180, "y": 58283, "w": 20, "h": 246, "m": 40, "v": 78}, {"x": 1414, "y": 58285, "w": 21, "h": 255, "m": 47, "v": 78}, {"x": 1582, "y": 58296, "w": 19, "h": 254, "m": 52, "v": 78}, {"x": 1816, "y": 58304, "w": 20, "h": 247, "m": 59, "v": 79}, {"x": 1917, "y": 58305, "w": 21, "h": 245, "m": 62, "v": 79}, {"x": 1984, "y": 58305, "w": 21, "h": 246, "m": 64, "v": 79}, {"x": 442, "y": 58313, "w": 20, "h": 65, "m": 18}, {"x": 2118, "y": 58315, "w": 20, "h": 237, "m": 68, "v": 75}, {"x": 3564, "y": 58350, "w": 19, "h": 56, "m": 111}, {"x": 3396, "y": 58503, "w": 19, "h": 64, "m": 106}, {"x": 3431, "y": 58766, "w": 20, "h": 64, "m": 107}, {"x": 945, "y": 58785, "w": 21, "h": 630, "m": 33, "v": 67}, {"x": 1751, "y": 58794, "w": 20, "h": 940, "m": 57, "v": 67}, {"x": 1348, "y": 58800, "w": 20, "h": 772, "m": 45, "v": 67}, {"x": 1885, "y": 58803, "w": 20, "h": 958, "m": 61, "v": 67}, {"x": 1986, "y": 58803, "w": 20, "h": 949, "m": 64, "v": 67}, {"x": 2153, "y": 58813, "w": 20, "h": 968, "m": 69, "v": 64}, {"x": 3396, "y": 58999, "w": 20, "h": 45, "m": 106}, {"x": 477, "y": 59563, "w": 20, "h": 55, "m": 19}, {"x": 3531, "y": 59591, "w": 21, "h": 54, "m": 110}, {"x": 3431, "y": 59776, "w": 20, "h": 63, "m": 107}, {"x": 1113, "y": 59872, "w": 21, "h": 963, "m": 38, "v": 56}, {"x": 1349, "y": 59909, "w": 20, "h": 989, "m": 45, "v": 57}, {"x": 1516, "y": 59918, "w": 21, "h": 676, "m": 50, "v": 57}, {"x": 1752, "y": 59928, "w": 19, "h": 1000, "m": 57, "v": 58}, {"x": 1919, "y": 59946, "w": 19, "h": 972, "m": 62, "v": 58}, {"x": 2053, "y": 59946, "w": 19, "h": 1008, "m": 66, "v": 58}, {"x": 2153, "y": 59948, "w": 21, "h": 974, "m": 69, "v": 54}, {"x": 443, "y": 59955, "w": 21, "h": 64, "m": 18}, {"x": 3565, "y": 59983, "w": 19, "h": 63, "m": 111}, {"x": 3396, "y": 60106, "w": 20, "h": 57, "m": 106}, {"x": 477, "y": 61051, "w": 20, "h": 55, "m": 19}, {"x": 3533, "y": 61098, "w": 20, "h": 46, "m": 110}, {"x": 946, "y": 61181, "w": 22, "h": 324, "m": 33, "v": 35}, {"x": 1349, "y": 61185, "w": 21, "h": 326, "m": 45, "v": 35}, {"x": 1752, "y": 61185, "w": 21, "h": 327, "m": 57, "v": 35}, {"x": 1887, "y": 61195, "w": 19, "h": 325, "m": 61, "v": 35}, {"x": 1987, "y": 61195, "w": 21, "h": 317, "m": 64, "v": 35}, {"x": 2155, "y": 61206, "w": 19, "h": 317, "m": 69, "v": 38}, {"x": 3432, "y": 61212, "w": 20, "h": 47, "m": 107}, {"x": 444, "y": 61231, "w": 21, "h": 56, "m": 18}, {"x": 3565, "y": 61259, "w": 20, "h": 56, "m": 111}, {"x": 3397, "y": 61393, "w": 20, "h": 38, "m": 106}, {"x": 3430, "y": 62865, "w": 20, "h": 46, "m": 107}, {"x": 509, "y": 64388, "w": 21, "h": 57, "m": 20}, {"x": 374, "y": 64391, "w": 21, "h": 57, "m": 16}, {"x": 441, "y": 64391, "w": 20, "h": 55, "m": 18}, {"x": 575, "y": 64391, "w": 22, "h": 55, "m": 22}, {"x": 3628, "y": 64402, "w": 20, "h": 56, "m": 113}, {"x": 3561, "y": 64409, "w": 20, "h": 47, "m": 111}, {"x": 3428, "y": 64410, "w": 19, "h": 46, "m": 107}, {"x": 3494, "y": 64410, "w": 20, "h": 47, "m": 109}, {"x": 473, "y": 64580, "w": 21, "h": 253, "m": 19}, {"x": 542, "y": 64590, "w": 21, "h": 234, "m": 21}, {"x": 3460, "y": 64618, "w": 20, "h": 225, "m": 108}, {"x": 3528, "y": 64626, "w": 20, "h": 235, "m": 110}, {"x": 405, "y": 64886, "w": 20, "h": 56, "m": 17}, {"x": 3594, "y": 64924, "w": 21, "h": 55, "m": 112}, {"x": 507, "y": 64975, "w": 20, "h": 46, "m": 20}, {"x": 439, "y": 64976, "w": 20, "h": 55, "m": 18}, {"x": 3493, "y": 65005, "w": 20, "h": 55, "m": 109}, {"x": 3559, "y": 65005, "w": 20, "h": 55, "m": 111}, {"x": 1142, "y": 65215, "w": 19, "h": 262, "m": 39, "v": 64}, {"x": 1544, "y": 65217, "w": 19, "h": 253, "m": 51, "v": 64}, {"x": 1678, "y": 65228, "w": 20, "h": 357, "m": 55, "v": 64}, {"x": 1780, "y": 65229, "w": 20, "h": 358, "m": 58, "v": 64}, {"x": 1947, "y": 65229, "w": 20, "h": 357, "m": 63, "v": 64}, {"x": 3390, "y": 65300, "w": 20, "h": 55, "m": 106}, {"x": 471, "y": 65389, "w": 21, "h": 55, "m": 19}, {"x": 973, "y": 65750, "w": 20, "h": 288, "m": 34, "v": 69}, {"x": 1376, "y": 65761, "w": 21, "h": 282, "m": 46, "v": 69}, {"x": 1611, "y": 65763, "w": 20, "h": 289, "m": 53, "v": 69}, {"x": 1777, "y": 65763, "w": 21, "h": 290, "m": 58, "v": 69}, {"x": 3424, "y": 65763, "w": 20, "h": 54, "m": 107}, {"x": 1911, "y": 65772, "w": 21, "h": 272, "m": 62, "v": 69}, {"x": 2013, "y": 65772, "w": 21, "h": 273, "m": 65, "v": 69}, {"x": 438, "y": 65781, "w": 19, "h": 73, "m": 18}, {"x": 3525, "y": 65828, "w": 20, "h": 44, "m": 110}, {"x": 470, "y": 65953, "w": 21, "h": 55, "m": 19}, {"x": 3388, "y": 65997, "w": 21, "h": 46, "m": 106}, {"x": 1140, "y": 66227, "w": 20, "h": 307, "m": 39, "v": 72}, {"x": 1542, "y": 66238, "w": 20, "h": 307, "m": 51, "v": 72}, {"x": 1677, "y": 66239, "w": 19, "h": 288, "m": 55, "v": 72}, {"x": 1777, "y": 66240, "w": 20, "h": 306, "m": 58, "v": 72}, {"x": 1944, "y": 66240, "w": 20, "h": 307, "m": 63, "v": 72}, {"x": 2078, "y": 66250, "w": 20, "h": 288, "m": 67, "v": 70}, {"x": 3423, "y": 66256, "w": 19, "h": 56, "m": 107}, {"x": 437, "y": 66257, "w": 19, "h": 63, "m": 18}, {"x": 3556, "y": 66284, "w": 20, "h": 64, "m": 111}, {"x": 470, "y": 66462, "w": 19, "h": 55, "m": 19}, {"x": 3524, "y": 66473, "w": 20, "h": 55, "m": 110}, {"x": 3388, "y": 66481, "w": 20, "h": 56, "m": 106}, {"x": 1040, "y": 66682, "w": 20, "h": 378, "m": 36, "v": 73}, {"x": 1441, "y": 66686, "w": 20, "h": 380, "m": 48, "v": 73}, {"x": 1708, "y": 66750, "w": 20, "h": 308, "m": 56, "v": 75}, {"x": 1844, "y": 66760, "w": 19, "h": 318, "m": 60, "v": 75}, {"x": 1944, "y": 66760, "w": 21, "h": 307, "m": 63, "v": 75}, {"x": 2111, "y": 66761, "w": 20, "h": 326, "m": 68, "v": 73}, {"x": 436, "y": 66777, "w": 20, "h": 55, "m": 18}, {"x": 3423, "y": 66777, "w": 19, "h": 64, "m": 107}, {"x": 3556, "y": 66815, "w": 19, "h": 64, "m": 111}, {"x": 3387, "y": 67003, "w": 20, "h": 37, "m": 106}, {"x": 3524, "y": 67004, "w": 19, "h": 46, "m": 110}, {"x": 469, "y": 67047, "w": 19, "h": 55, "m": 19}, {"x": 1139, "y": 67226, "w": 20, "h": 331, "m": 39, "v": 73}, {"x": 1541, "y": 67235, "w": 20, "h": 333, "m": 51, "v": 73}, {"x": 1944, "y": 67246, "w": 20, "h": 333, "m": 63, "v": 74}, {"x": 1777, "y": 67247, "w": 20, "h": 323, "m": 58, "v": 74}, {"x": 2078, "y": 67248, "w": 20, "h": 322, "m": 67, "v": 76}, {"x": 436, "y": 67264, "w": 19, "h": 55, "m": 18}, {"x": 3423, "y": 67265, "w": 19, "h": 55, "m": 107}, {"x": 3556, "y": 67282, "w": 19, "h": 57, "m": 111}, {"x": 3387, "y": 67482, "w": 20, "h": 70, "m": 106}, {"x": 3523, "y": 67499, "w": 20, "h": 63, "m": 110}, {"x": 468, "y": 67540, "w": 20, "h": 56, "m": 19}, {"x": 368, "y": 67640, "w": 20, "h": 55, "m": 16}, {"x": 3623, "y": 67651, "w": 20, "h": 64, "m": 113}, {"x": 870, "y": 67703, "w": 21, "h": 406, "m": 31, "v": 70}, {"x": 1271, "y": 67716, "w": 20, "h": 388, "m": 43, "v": 70}, {"x": 1775, "y": 67783, "w": 20, "h": 333, "m": 58, "v": 70}, {"x": 1943, "y": 67783, "w": 20, "h": 397, "m": 63, "v": 70}, {"x": 2076, "y": 67794, "w": 21, "h": 377, "m": 67, "v": 79}, {"x": 2176, "y": 67794, "w": 20, "h": 378, "m": 70, "v": 79}, {"x": 3422, "y": 67800, "w": 19, "h": 63, "m": 107}, {"x": 434, "y": 67811, "w": 20, "h": 54, "m": 18}, {"x": 3555, "y": 67845, "w": 19, "h": 64, "m": 111}, {"x": 3387, "y": 68032, "w": 19, "h": 56, "m": 106}, {"x": 467, "y": 68142, "w": 20, "h": 56, "m": 19}, {"x": 3522, "y": 68177, "w": 19, "h": 56, "m": 110}, {"x": 902, "y": 68217, "w": 21, "h": 577, "m": 32, "v": 64}, {"x": 1305, "y": 68267, "w": 20, "h": 532, "m": 44, "v": 65}, {"x": 3420, "y": 68322, "w": 20, "h": 72, "m": 107}, {"x": 1942, "y": 68331, "w": 20, "h": 470, "m": 63, "v": 67}, {"x": 1841, "y": 68332, "w": 21, "h": 478, "m": 60, "v": 67}, {"x": 2110, "y": 68333, "w": 19, "h": 342, "m": 68, "v": 75}, {"x": 434, "y": 68349, "w": 21, "h": 73, "m": 18}, {"x": 3554, "y": 68385, "w": 19, "h": 55, "m": 111}, {"x": 2076, "y": 68684, "w": 20, "h": 207, "m": 67, "v": 68}, {"x": 3386, "y": 68708, "w": 19, "h": 56, "m": 106}, {"x": 467, "y": 68906, "w": 20, "h": 65, "m": 19}, {"x": 3520, "y": 68960, "w": 21, "h": 55, "m": 110}, {"x": 3421, "y": 69013, "w": 19, "h": 64, "m": 107}, {"x": 969, "y": 69027, "w": 20, "h": 290, "m": 34, "v": 57}, {"x": 1774, "y": 69033, "w": 21, "h": 397, "m": 58, "v": 57}, {"x": 1372, "y": 69041, "w": 21, "h": 307, "m": 46, "v": 57}, {"x": 2009, "y": 69042, "w": 21, "h": 406, "m": 65, "v": 57}, {"x": 1909, "y": 69043, "w": 19, "h": 387, "m": 62, "v": 57}, {"x": 467, "y": 69168, "w": 21, "h": 181, "m": 19}, {"x": 536, "y": 69168, "w": 21, "h": 181, "m": 21}, {"x": 3453, "y": 69194, "w": 20, "h": 189, "m": 108}, {"x": 3521, "y": 69202, "w": 20, "h": 173, "m": 110}, {"x": 3385, "y": 69230, "w": 20, "h": 55, "m": 106}, {"x": 399, "y": 69410, "w": 21, "h": 56, "m": 17}, {"x": 3588, "y": 69438, "w": 20, "h": 54, "m": 112}, {"x": 434, "y": 69490, "w": 20, "h": 63, "m": 18}, {"x": 3553, "y": 69515, "w": 21, "h": 56, "m": 111}, {"x": 3420, "y": 69623, "w": 20, "h": 55, "m": 107}, {"x": 1103, "y": 69719, "w": 21, "h": 210, "m": 38, "v": 79}, {"x": 1506, "y": 69720, "w": 21, "h": 219, "m": 50, "v": 79}, {"x": 2009, "y": 69731, "w": 20, "h": 288, "m": 65, "v": 79}, {"x": 1773, "y": 69732, "w": 21, "h": 297, "m": 58, "v": 79}, {"x": 2175, "y": 69733, "w": 20, "h": 297, "m": 70, "v": 85}, {"x": 1908, "y": 69740, "w": 19, "h": 280, "m": 62, "v": 79}, {"x": 3385, "y": 69875, "w": 20, "h": 54, "m": 106}, {"x": 466, "y": 69904, "w": 20, "h": 54, "m": 19}, {"x": 3520, "y": 69928, "w": 20, "h": 63, "m": 110}, {"x": 3419, "y": 70195, "w": 20, "h": 47, "m": 107}, {"x": 1538, "y": 70196, "w": 20, "h": 262, "m": 51, "v": 82}, {"x": 1137, "y": 70204, "w": 19, "h": 243, "m": 39, "v": 82}, {"x": 1773, "y": 70207, "w": 20, "h": 253, "m": 58, "v": 82}, {"x": 1941, "y": 70216, "w": 20, "h": 235, "m": 63, "v": 83}, {"x": 2074, "y": 70217, "w": 22, "h": 243, "m": 67, "v": 87}, {"x": 434, "y": 70234, "w": 19, "h": 63, "m": 18}, {"x": 3552, "y": 70277, "w": 20, "h": 56, "m": 111}, {"x": 3384, "y": 70375, "w": 20, "h": 56, "m": 106}, {"x": 466, "y": 70450, "w": 19, "h": 63, "m": 19}, {"x": 3520, "y": 70487, "w": 20, "h": 53, "m": 110}, {"x": 1036, "y": 70614, "w": 21, "h": 317, "m": 36, "v": 82}, {"x": 1437, "y": 70645, "w": 21, "h": 291, "m": 48, "v": 82}, {"x": 3419, "y": 70662, "w": 20, "h": 46, "m": 107}, {"x": 1941, "y": 70682, "w": 20, "h": 247, "m": 63, "v": 83}, {"x": 2075, "y": 70683, "w": 20, "h": 256, "m": 67, "v": 88}, {"x": 432, "y": 70691, "w": 20, "h": 65, "m": 18}, {"x": 2243, "y": 70691, "w": 20, "h": 239, "m": 72, "v": 88}, {"x": 2343, "y": 70693, "w": 19, "h": 246, "m": 75, "v": 88}, {"x": 3553, "y": 70726, "w": 19, "h": 65, "m": 111}, {"x": 3384, "y": 70836, "w": 20, "h": 55, "m": 106}, {"x": 465, "y": 70963, "w": 20, "h": 55, "m": 19}, {"x": 3520, "y": 70988, "w": 20, "h": 46, "m": 110}, {"x": 366, "y": 71063, "w": 19, "h": 55, "m": 16}, {"x": 3619, "y": 71089, "w": 21, "h": 56, "m": 113}, {"x": 1202, "y": 71132, "w": 20, "h": 334, "m": 41, "v": 81}, {"x": 1606, "y": 71134, "w": 20, "h": 334, "m": 53, "v": 81}, {"x": 1907, "y": 71134, "w": 20, "h": 324, "m": 62, "v": 81}, {"x": 2008, "y": 71142, "w": 20, "h": 327, "m": 65, "v": 81}, {"x": 2174, "y": 71144, "w": 20, "h": 335, "m": 70, "v": 87}, {"x": 2309, "y": 71146, "w": 19, "h": 341, "m": 74, "v": 87}, {"x": 3419, "y": 71168, "w": 19, "h": 45, "m": 107}, {"x": 432, "y": 71170, "w": 20, "h": 55, "m": 18}, {"x": 3552, "y": 71195, "w": 20, "h": 55, "m": 111}, {"x": 3384, "y": 71401, "w": 20, "h": 48, "m": 106}, {"x": 465, "y": 71459, "w": 20, "h": 53, "m": 19}, {"x": 3519, "y": 71491, "w": 20, "h": 46, "m": 110}, {"x": 1201, "y": 71650, "w": 20, "h": 299, "m": 41, "v": 80}, {"x": 1604, "y": 71652, "w": 20, "h": 307, "m": 53, "v": 80}, {"x": 2007, "y": 71652, "w": 20, "h": 307, "m": 65, "v": 80}, {"x": 2242, "y": 71654, "w": 19, "h": 299, "m": 72, "v": 85}, {"x": 2140, "y": 71655, "w": 20, "h": 316, "m": 69, "v": 85}, {"x": 431, "y": 71663, "w": 20, "h": 55, "m": 18}, {"x": 3419, "y": 71669, "w": 19, "h": 37, "m": 107}, {"x": 3551, "y": 71698, "w": 21, "h": 63, "m": 111}, {"x": 3383, "y": 71893, "w": 20, "h": 64, "m": 106}, {"x": 1370, "y": 72112, "w": 20, "h": 1142, "m": 46, "v": 69}, {"x": 1772, "y": 72114, "w": 19, "h": 1160, "m": 58, "v": 69}, {"x": 1604, "y": 72131, "w": 20, "h": 1143, "m": 53, "v": 69}, {"x": 1904, "y": 72141, "w": 22, "h": 1124, "m": 62, "v": 68}, {"x": 2006, "y": 72149, "w": 21, "h": 1124, "m": 65, "v": 68}, {"x": 2173, "y": 72160, "w": 20, "h": 1106, "m": 70, "v": 75}, {"x": 3418, "y": 72200, "w": 19, "h": 46, "m": 107}, {"x": 3383, "y": 72397, "w": 19, "h": 48, "m": 106}, {"x": 462, "y": 72993, "w": 20, "h": 64, "m": 19}, {"x": 3416, "y": 73270, "w": 20, "h": 55, "m": 107}, {"x": 531, "y": 73362, "w": 21, "h": 46, "m": 21}, {"x": 1368, "y": 73369, "w": 20, "h": 295, "m": 46, "v": 59}, {"x": 1770, "y": 73370, "w": 19, "h": 330, "m": 58, "v": 59}, {"x": 2005, "y": 73414, "w": 21, "h": 305, "m": 65, "v": 70}, {"x": 1904, "y": 73415, "w": 19, "h": 295, "m": 62, "v": 71}, {"x": 429, "y": 73433, "w": 20, "h": 54, "m": 18}, {"x": 3516, "y": 73502, "w": 20, "h": 46, "m": 110}, {"x": 3380, "y": 73519, "w": 20, "h": 46, "m": 106}, {"x": 461, "y": 73593, "w": 20, "h": 64, "m": 19}, {"x": 3448, "y": 73662, "w": 19, "h": 19, "m": 108}, {"x": 2070, "y": 73682, "w": 20, "h": 100, "m": 67, "v": 51}, {"x": 1433, "y": 73886, "w": 19, "h": 335, "m": 48, "v": 70}, {"x": 1700, "y": 73895, "w": 19, "h": 337, "m": 56, "v": 70}, {"x": 1834, "y": 73896, "w": 22, "h": 388, "m": 60, "v": 70}, {"x": 1935, "y": 73896, "w": 21, "h": 397, "m": 63, "v": 70}, {"x": 2103, "y": 73906, "w": 21, "h": 379, "m": 68, "v": 60}, {"x": 3414, "y": 73910, "w": 20, "h": 47, "m": 107}, {"x": 428, "y": 73915, "w": 19, "h": 54, "m": 18}, {"x": 3547, "y": 73938, "w": 21, "h": 64, "m": 111}, {"x": 3379, "y": 74101, "w": 20, "h": 46, "m": 106}, {"x": 3515, "y": 74155, "w": 20, "h": 56, "m": 110}, {"x": 461, "y": 74159, "w": 21, "h": 55, "m": 19}, {"x": 3414, "y": 74351, "w": 19, "h": 46, "m": 107}, {"x": 1432, "y": 74360, "w": 20, "h": 256, "m": 48, "v": 69}, {"x": 1935, "y": 74371, "w": 20, "h": 318, "m": 63, "v": 69}, {"x": 1699, "y": 74372, "w": 20, "h": 245, "m": 56, "v": 69}, {"x": 1835, "y": 74373, "w": 20, "h": 308, "m": 60, "v": 69}, {"x": 2102, "y": 74381, "w": 21, "h": 327, "m": 68, "v": 61}, {"x": 427, "y": 74390, "w": 20, "h": 56, "m": 18}, {"x": 3547, "y": 74425, "w": 20, "h": 56, "m": 111}, {"x": 3378, "y": 74559, "w": 21, "h": 65, "m": 106}, {"x": 460, "y": 74562, "w": 20, "h": 64, "m": 19}, {"x": 3514, "y": 74605, "w": 20, "h": 46, "m": 110}, {"x": 3413, "y": 74838, "w": 19, "h": 37, "m": 107}, {"x": 1096, "y": 74848, "w": 20, "h": 315, "m": 38, "v": 70}, {"x": 1499, "y": 74848, "w": 20, "h": 299, "m": 50, "v": 70}, {"x": 1767, "y": 74849, "w": 19, "h": 308, "m": 58, "v": 70}, {"x": 1900, "y": 74849, "w": 21, "h": 307, "m": 62, "v": 70}, {"x": 2002, "y": 74849, "w": 20, "h": 316, "m": 65, "v": 70}, {"x": 2102, "y": 74851, "w": 19, "h": 316, "m": 68, "v": 63}, {"x": 426, "y": 74859, "w": 20, "h": 65, "m": 18}, {"x": 3546, "y": 74894, "w": 20, "h": 64, "m": 111}, {"x": 459, "y": 74986, "w": 20, "h": 54, "m": 19}, {"x": 3512, "y": 75028, "w": 21, "h": 47, "m": 110}, {"x": 3378, "y": 75056, "w": 20, "h": 63, "m": 106}, {"x": 1129, "y": 75296, "w": 20, "h": 251, "m": 39, "v": 70}, {"x": 1531, "y": 75296, "w": 20, "h": 269, "m": 51, "v": 70}, {"x": 1766, "y": 75298, "w": 21, "h": 260, "m": 58, "v": 70}, {"x": 426, "y": 75308, "w": 20, "h": 55, "m": 18}, {"x": 1934, "y": 75308, "w": 21, "h": 259, "m": 63, "v": 70}, {"x": 2068, "y": 75308, "w": 21, "h": 260, "m": 67, "v": 68}, {"x": 3413, "y": 75314, "w": 19, "h": 47, "m": 107}, {"x": 3377, "y": 75520, "w": 20, "h": 46, "m": 106}, {"x": 458, "y": 75531, "w": 20, "h": 54, "m": 19}, {"x": 1296, "y": 75718, "w": 20, "h": 387, "m": 44, "v": 69}, {"x": 1697, "y": 75756, "w": 19, "h": 369, "m": 56, "v": 70}, {"x": 1933, "y": 75809, "w": 21, "h": 414, "m": 63, "v": 70}, {"x": 2235, "y": 75809, "w": 20, "h": 425, "m": 72, "v": 75}, {"x": 2067, "y": 75811, "w": 20, "h": 422, "m": 67, "v": 75}, {"x": 3412, "y": 75815, "w": 19, "h": 46, "m": 107}, {"x": 424, "y": 75819, "w": 20, "h": 64, "m": 18}, {"x": 1832, "y": 75819, "w": 20, "h": 414, "m": 60, "v": 70}, {"x": 3545, "y": 75861, "w": 19, "h": 55, "m": 111}, {"x": 3377, "y": 76049, "w": 19, "h": 64, "m": 106}, {"x": 458, "y": 76276, "w": 20, "h": 55, "m": 19}, {"x": 3512, "y": 76292, "w": 20, "h": 55, "m": 110}, {"x": 1296, "y": 76381, "w": 20, "h": 299, "m": 44, "v": 62}, {"x": 1697, "y": 76383, "w": 19, "h": 317, "m": 56, "v": 62}, {"x": 2001, "y": 76391, "w": 20, "h": 308, "m": 65, "v": 62}, {"x": 1832, "y": 76393, "w": 21, "h": 316, "m": 60, "v": 62}, {"x": 2101, "y": 76394, "w": 19, "h": 297, "m": 68, "v": 67}, {"x": 2235, "y": 76394, "w": 20, "h": 299, "m": 72, "v": 67}, {"x": 424, "y": 76401, "w": 20, "h": 55, "m": 18}, {"x": 3411, "y": 76408, "w": 20, "h": 63, "m": 107}, {"x": 3545, "y": 76426, "w": 19, "h": 64, "m": 111}, {"x": 3377, "y": 76651, "w": 19, "h": 55, "m": 106}, {"x": 1262, "y": 76822, "w": 19, "h": 459, "m": 43, "v": 52}, {"x": 1497, "y": 76889, "w": 21, "h": 412, "m": 50, "v": 50}, {"x": 1664, "y": 76889, "w": 21, "h": 394, "m": 55, "v": 50}, {"x": 1799, "y": 76933, "w": 20, "h": 369, "m": 59, "v": 49}, {"x": 1900, "y": 76935, "w": 20, "h": 358, "m": 62, "v": 49}, {"x": 2067, "y": 76936, "w": 20, "h": 367, "m": 67, "v": 56}, {"x": 2202, "y": 76980, "w": 19, "h": 323, "m": 71, "v": 54}, {"x": 3412, "y": 76985, "w": 19, "h": 46, "m": 107}, {"x": 3376, "y": 77228, "w": 21, "h": 54, "m": 106}, {"x": 458, "y": 77274, "w": 20, "h": 46, "m": 19}, {"x": 3512, "y": 77299, "w": 20, "h": 55, "m": 110}, {"x": 3411, "y": 77603, "w": 19, "h": 52, "m": 107}, {"x": 526, "y": 77676, "w": 21, "h": 28, "m": 21}, {"x": 3445, "y": 77700, "w": 18, "h": 27, "m": 108}, {"x": 1663, "y": 77720, "w": 20, "h": 252, "m": 55, "v": 61}, {"x": 1798, "y": 77720, "w": 20, "h": 252, "m": 59, "v": 61}, {"x": 1261, "y": 77727, "w": 20, "h": 243, "m": 43, "v": 62}, {"x": 1898, "y": 77729, "w": 21, "h": 245, "m": 62, "v": 62}, {"x": 2066, "y": 77730, "w": 20, "h": 236, "m": 67, "v": 64}, {"x": 2200, "y": 77730, "w": 21, "h": 235, "m": 71, "v": 64}, {"x": 3376, "y": 77790, "w": 20, "h": 55, "m": 106}, {"x": 1296, "y": 78187, "w": 21, "h": 395, "m": 44, "v": 70}, {"x": 1697, "y": 78207, "w": 20, "h": 358, "m": 56, "v": 70}, {"x": 1934, "y": 78233, "w": 19, "h": 351, "m": 63, "v": 70}, {"x": 2101, "y": 78234, "w": 19, "h": 359, "m": 68, "v": 75}, {"x": 2234, "y": 78235, "w": 22, "h": 360, "m": 72, "v": 75}, {"x": 425, "y": 78250, "w": 20, "h": 55, "m": 18}, {"x": 3545, "y": 78276, "w": 19, "h": 64, "m": 111}, {"x": 3411, "y": 78285, "w": 19, "h": 36, "m": 107}, {"x": 3377, "y": 78509, "w": 19, "h": 64, "m": 106}, {"x": 457, "y": 78547, "w": 21, "h": 64, "m": 19}, {"x": 3512, "y": 78572, "w": 20, "h": 55, "m": 110}, {"x": 893, "y": 78829, "w": 20, "h": 262, "m": 32, "v": 70}, {"x": 1296, "y": 78832, "w": 20, "h": 299, "m": 44, "v": 70}, {"x": 2100, "y": 78836, "w": 20, "h": 342, "m": 68, "v": 74}, {"x": 1833, "y": 78844, "w": 20, "h": 343, "m": 60, "v": 70}, {"x": 2001, "y": 78844, "w": 20, "h": 343, "m": 65, "v": 70}, {"x": 3412, "y": 78850, "w": 19, "h": 55, "m": 107}, {"x": 425, "y": 78853, "w": 19, "h": 55, "m": 18}, {"x": 3545, "y": 78878, "w": 19, "h": 64, "m": 111}, {"x": 3377, "y": 79023, "w": 20, "h": 45, "m": 106}, {"x": 458, "y": 79185, "w": 20, "h": 55, "m": 19}, {"x": 3512, "y": 79220, "w": 20, "h": 56, "m": 110}, {"x": 960, "y": 79342, "w": 21, "h": 403, "m": 34, "v": 66}, {"x": 1364, "y": 79355, "w": 19, "h": 403, "m": 46, "v": 66}, {"x": 2067, "y": 79376, "w": 20, "h": 393, "m": 67, "v": 71}, {"x": 1765, "y": 79383, "w": 20, "h": 386, "m": 58, "v": 67}, {"x": 1933, "y": 79392, "w": 20, "h": 376, "m": 63, "v": 67}, {"x": 3411, "y": 79409, "w": 20, "h": 46, "m": 107}, {"x": 425, "y": 79410, "w": 19, "h": 65, "m": 18}, {"x": 3545, "y": 79445, "w": 20, "h": 63, "m": 111}, {"x": 3377, "y": 79605, "w": 20, "h": 46, "m": 106}, {"x": 457, "y": 79822, "w": 20, "h": 55, "m": 19}, {"x": 960, "y": 79926, "w": 20, "h": 701, "m": 34, "v": 60}, {"x": 1364, "y": 79937, "w": 19, "h": 694, "m": 46, "v": 60}, {"x": 1765, "y": 80010, "w": 21, "h": 631, "m": 58, "v": 62}, {"x": 1899, "y": 80018, "w": 21, "h": 623, "m": 62, "v": 62}, {"x": 2000, "y": 80018, "w": 21, "h": 632, "m": 65, "v": 62}, {"x": 425, "y": 80038, "w": 20, "h": 55, "m": 18}, {"x": 3411, "y": 80061, "w": 20, "h": 55, "m": 107}, {"x": 3377, "y": 80269, "w": 19, "h": 73, "m": 106}, {"x": 1697, "y": 80387, "w": 19, "h": 254, "m": 56, "v": 54}, {"x": 458, "y": 80641, "w": 20, "h": 63, "m": 19}, {"x": 1127, "y": 80799, "w": 21, "h": 1050, "m": 39, "v": 52}, {"x": 1530, "y": 80801, "w": 20, "h": 1040, "m": 51, "v": 52}, {"x": 1665, "y": 80801, "w": 19, "h": 1067, "m": 55, "v": 52}, {"x": 1364, "y": 80810, "w": 20, "h": 1021, "m": 46, "v": 52}, {"x": 1766, "y": 80811, "w": 19, "h": 1067, "m": 58, "v": 52}, {"x": 1933, "y": 80820, "w": 21, "h": 1049, "m": 63, "v": 52}, {"x": 425, "y": 80838, "w": 19, "h": 55, "m": 18}, {"x": 3412, "y": 80898, "w": 19, "h": 64, "m": 107}, {"x": 3376, "y": 81079, "w": 20, "h": 55, "m": 106}, {"x": 458, "y": 81689, "w": 19, "h": 64, "m": 19}, {"x": 3411, "y": 82073, "w": 20, "h": 53, "m": 107}, {"x": 1530, "y": 82179, "w": 20, "h": 1070, "m": 51, "v": 44}, {"x": 894, "y": 82185, "w": 19, "h": 863, "m": 32, "v": 44}, {"x": 1295, "y": 82189, "w": 21, "h": 863, "m": 44, "v": 44}, {"x": 1698, "y": 82191, "w": 19, "h": 1050, "m": 56, "v": 44}, {"x": 1832, "y": 82191, "w": 21, "h": 1088, "m": 60, "v": 44}, {"x": 1933, "y": 82199, "w": 21, "h": 1097, "m": 63, "v": 45}, {"x": 425, "y": 82216, "w": 20, "h": 73, "m": 18}, {"x": 3377, "y": 82340, "w": 19, "h": 54, "m": 106}, {"x": 458, "y": 83367, "w": 19, "h": 55, "m": 19}, {"x": 726, "y": 83564, "w": 20, "h": 603, "m": 27, "v": 35}, {"x": 1530, "y": 83569, "w": 20, "h": 613, "m": 51, "v": 35}, {"x": 1665, "y": 83571, "w": 19, "h": 638, "m": 55, "v": 35}, {"x": 1128, "y": 83577, "w": 20, "h": 586, "m": 39, "v": 35}, {"x": 1766, "y": 83579, "w": 19, "h": 595, "m": 58, "v": 35}, {"x": 1933, "y": 83579, "w": 21, "h": 631, "m": 63, "v": 35}, {"x": 3412, "y": 83612, "w": 19, "h": 100, "m": 107}, {"x": 425, "y": 83644, "w": 20, "h": 54, "m": 18}, {"x": 494, "y": 83650, "w": 20, "h": 46, "m": 20}, {"x": 560, "y": 83652, "w": 20, "h": 46, "m": 22}, {"x": 359, "y": 83653, "w": 19, "h": 46, "m": 16}, {"x": 3545, "y": 83657, "w": 20, "h": 56, "m": 111}, {"x": 3478, "y": 83658, "w": 21, "h": 55, "m": 109}, {"x": 3613, "y": 83659, "w": 20, "h": 55, "m": 113}, {"x": 3376, "y": 83803, "w": 20, "h": 36, "m": 106}, {"x": 3412, "y": 85541, "w": 20, "h": 46, "m": 107}, {"x": 3310, "y": 87776, "w": 21, "h": 873, "m": 104}]}